{
    "2691101": {},
    "2691102": {
        "عنوان و  نام پديدآور": "ایران : جهش اقتصادی ویژه نامه هدفمندی یارانهها[پیایند: روزنامه]",
        "مشخصات نشر": "تهران: [خبرگزاری جمهوری اسلامی(ایرنا)]،  ۱۳۹۰ -",
        "فاصله انتشار": "بدون قاعده ",
        "یادداشت": "ضمیمه روزنامه ایران",
        "يادداشت": "صاحب امتیاز: خبرگزاری جمهوری اسلامی(ایرنا)\nمدیرمسئول: مصیب نعیمی\nناظر ویژه نامه: غلامحسین اسلامیفرد\nسردبیر: اصغر بالسینی\nدبیر ویژه نامه: مهدی رجبی",
        "شماره کتابشناسی ملی": "۲۶۹۱۱۰۲",
        "زبان اثر": "فارسی"
    },
    "2691103": {
        "دسترسي به فايل تمام متن": "برای دستیابی به فایل تمام متن منبع، به \"تالار منابع رقمی\" مراجعه فرمایید. Ø¢Ø¯Ø±Ø³ Ø§ÙÚ©ØªØ±ÙÙÛÚ©Û ÙÙØ¨Ø¹ ",
        "شماره بازیابی": "۵۱-۷۰۳۱۸",
        "شماره کتابشناسی ملی": "۲۶۹۱۱۰۳",
        "پدیدآور": "شفیعپور، مریم",
        "عنوان و  نام پديدآور": "بررسی میزان بیان پروتئینهای خانواده سپتین در مردان نابارور مراجعهکننده به مرکز ناباروری رویان [پ‍ای‍انن‍ام‍ه]/ نگارش مریم شفیعپور ؛ استاد راهنما محمدعلی صدیقیگیلانی، استاد راهنمای همکار شاهحسینی؛ استاد مشاور حاجیحسینی.",
        "مقطع و رشته تحصیلی": "(کارشناسی ارشد): بیوشیمی.",
        "محل و سال اخذ مدرک": "، ۱۳۸۹.",
        "نام دانشگاه/ پژوهشگاه": "دانشگاه پیام نور، دانشکده علوم پایه، گروه علمی زیستشناسی- بیوشیمی.",
        "مشخصات نشر": "۱۳۸۹.",
        "مشخصات ظاهری": "م، ۱۱۲ ورق: مصور، جدول، نمودار.",
        "يادداشت": "چکیده: فارسی- انگلیسی.",
        "یادداشت": "کتابنامه: ص. ۱۰۷-۱۱۱.",
        "شناسه افزوده": "ص‍دی‍ق‍ی گ‍ی‍لان‍ی، م‍ح‍م‍د ع‍ل‍ی، استاد راهنما ، استاد راهنماشاهحسینی، مریم حاجیحسینی بغدادآبادی، رضا، ۱۳۴۴ - ، استاد مشاور دانشگاه پیام نور. دانشکده علوم پایه. گروه زیستشناسی",
        "توصیفگر": "م‍ردان\nن‍اب‍اروری\nسپتینها"
    },
    "2691104": {
        "وضعیت نمایه سازی": "اطلاعات ثبت",
        "شماره کتابشناسی ملی": "۲۶۹۱۱۰۴",
        "شماره واسپاری قانونی": "۶۱۲۲ و",
        "عنوان و  نام پديدآور": "نمیشه [نوار موسیقی]/مجید رضازاده",
        "وضعيت نشر": "[تهران]: نوای رامشه،  [××۱۳]",
        "مشخصات ظاهری": "۱ نوار کاست (ح. '۶۰): با کلام"
    },
    "2691105": {
        "شماره کتابشناسی ملی": "۲۶۹۱۱۰۵",
        "عنوان و  نام پديدآور": "عالم نسوان [ميکروفرم] : ۱۳۰۰-۱۳۰۶ شمسی",
        "وضعيت نشر": "[تهران]: کتابخانه ملی جمهوری اسلامی ایران، واحد میکروگرافیک،  [××۱۳]",
        "مشخصات ظاهری": "۱حلقه میکروفیلم: مصور؛ ۳۴مم.",
        "يادداشت": "عالم نسوان، سالهای ۲،۳،۴،۶،۷ (۱۳۰۰ لغایت ۱۳۰۶ شمسی)\nشماره بازیابی نشریات ۸۴م-نگاتیو\nدر داخل جلد سال ۱۳۰۶ آمده ولی در اطلاعات روی جلد سال ۱۳۰۶ نیامده"
    },
    "2691106": {},
    "2691107": {},
    "2691108": {
        "وضعیت نمایه سازی": "فیپا",
        "شماره کتابشناسی ملی": "۲۶۹۱۱۰۸",
        "عنوان و  نام پديدآور": "مطبوعات عصر پهلوی [منابع الکترونیکی: کتاب]: روزنامه مرد مبارز/ [گردآورنده] مرکز بررسی اسناد تاریخی.",
        "وضعيت نشر": "تهران: وزارت اطلاعات، مرکز بررسی اسناد تاریخی،  ۱۳۹۰.",
        "مشخصات ظاهری": "۱ لوحفشرده: رنگی٬ بیکلام؛ ۱۲ سم.",
        "يادداشت": "متن چاپی: وزارت اطلاعات، مرکز بررسی اسناد تاریخی، ۱۳۸۵، ۵۰۰ ص. ",
        "عنوان ديگر": "روزنامه مرد مبارز.",
        "توصیفگر": "سازمان اطلاعات و امنیت کشور مرد مبارز (روزنامه) روزن‍ام‍هه‍ا\nدوره پ‍ه‍ل‍وی\nاسناد سیاسی",
        "شناسه افزوده": "ایران. وزارت اطلاعات. مرکز بررسی اسناد تاریخی"
    },
    "2691109": {},
    "2691110": {},
    "2691111": {},
    "2691112": {
        "شناسه  سند": "۲۹۳/۵۲۲۵۱",
        "عنوان": "اقدامات حزب رستاخیز ملت ایران در بندر ماهشهر[سند]",
        "منشا": "استانداری خوزستان",
        "تاریخ /دوره ایجاد": "۱۳۵۶-۵۴.",
        "مشخصات ظاهری": "۱۹۵برگ.",
        "دامنه و محتوا": "اقدامات حزب رستاخیز ملت ایران در بندر ماهشهر ، اساسنامه و مرامنامه حزب ،نشریه خبرگزاری پارس راجع به حزب رستاخیز ملت ایران.",
        "توصیفگر": "حزب رستاخیز ملت ایران\nخبرگزاری پارس\nHizb Rastakhiz Mellate Iran مرامنامه\nاساسنامهها بندر ماهشهر",
        "مركز نگهداري سند": "آرشيو ملي ايران",
        "شناسه سند": "۲۹۳/۵۲۲۵۱"
    },
    "2691113": {
        "وضعیت نمایه سازی": "اطلاعات ثبت",
        "شماره کتابشناسی ملی": "۲۶۹۱۱۱۳",
        "عنوان و  نام پديدآور": "The Immortal works of Ketelbey[Sound disc, Musical]/Stanford Robinsob.",
        "وضعيت نشر": "England: Decca, [19xx].",
        "مشخصات ظاهری": "۱ صفحه (ح’۱۴): آنالوگ٬ ۷۸ دور٬ باکلام؛ ۳۰سم.",
        "يادداشت": "زبان : انگلیسی."
    },
    "2691114": {},
    "2691115": {
        "وضعیت نمایه سازی": "اطلاعات ثبت",
        "شماره کتابشناسی ملی": "۲۶۹۱۱۱۵",
        "عنوان و  نام پديدآور": "سلام بر گل نرگس! [کارت]",
        "وضعيت نشر": " تهران:  گلستان کوثر،   [××۱۳].",
        "مشخصات ظاهری": "۱کارت:  رنگی؛ ۱۶×۱۲س م. (تاشده۸×۱۲س م. )",
        "يادداشت": "(صالح:۲۴۲)",
        "خلاصه": "دسته گل نرگس و بنفشه"
    },
    "2691116": {},
    "2691117": {},
    "2691118": {
        "عنوان و  نام پديدآور": "جام جم:ویژه نامه [پیایند: روزنامه]",
        "مشخصات نشر": "تهران: [روزنامه جام جم]،  ۱۳۹۰ -",
        "فاصله انتشار": "بدون قاعده ",
        "یادداشت": "ویژهنامه سال جهانی سازمان داوطلبان جمعیت هلال احمر",
        "شماره کتابشناسی ملی": "۲۶۹۱۱۱۸",
        "زبان اثر": "فارسی"
    },
    "2691119": {},
    "2691120": {
        "وضعیت نمایه سازی": "فیپا",
        "شماره کتابشناسی ملی": "۲۶۹۱۱۲۰",
        "عنوان و  نام پديدآور": "مطبوعات عصر پهلوی [منابع الکترونیکی: کتاب]: روزنامه فرمان/ [گردآورنده] مرکز بررسی اسناد تاریخی.",
        "وضعيت نشر": "تهران: وزارت اطلاعات، مرکز بررسی اسناد تاریخی،  ۱۳۹۰.",
        "مشخصات ظاهری": "۱ لوحفشرده: رنگی٬ بیکلام؛ ۱۲ سم.",
        "يادداشت": "متن چاپی: وزارت اطلاعات، مرکز بررسی اسناد تاریخی، ۱۳۸۴، ۵۵۶ ص. ",
        "عنوان ديگر": "روزنامه فرمان.",
        "توصیفگر": "سازمان اطلاعات و امنیت کشور فرمان (روزنامه) روزن‍ام‍هه‍ا\nدوره پ‍ه‍ل‍وی\nاسناد سیاسی",
        "شناسه افزوده": "ایران. وزارت اطلاعات. مرکز بررسی اسناد تاریخی"
    },
    "2691121": {},
    "2691122": {},
    "2691123": {
        "سرشناسه": "قادریفر، فرشید",
        "عنوان و نام پديدآور": "کنترل و گواهی بذر( کتاب درسی همراه با سوالات کنکور) [کتاب] / تالیف فرشید قادریفر، افشین سلطانی.",
        "مشخصات نشر": "مشهد: جهاد دانشگاهی، واحد مشهد، انتشارات، ۱۳۸۹.",
        "مشخصات ظاهری": "۲۰۰ ص.",
        "فروست": "جهاد دانشگاهی مشهد؛ ۴۰۷.",
        "شابک": "۴۰۰۰۰ ریال:964-324-215-2 ؛  ۶۵۰۰۰ ریالچاپ دوم:978-964-324-215-2",
        "يادداشت": "پشت جلد به انگلیسی: Farshid Ghaderi far, Afshin Soltani. Seed testing and control... چاپ دوم:۱۳۹۲.",
        "یادداشت": "کتابنامه: ص. ۱۹۷- ۲۰۰.",
        "موضوع": "بذرها -- گواهی و گواهینامهها بذرها -- بازرسی و کنترل بذرها -- گواهی و گواهینامهها -- آزمونها و تمرینها (عالی) ",
        "شناسه افزوده": "س‍ل‍طان‍ی، اف‍ش‍ی‍ن، ۱۳۵۰- جهاد دانشگاهی. واحد مشهد",
        "رده بندی کنگره": "SB۱۱۴ /آ۳ق۲ ۱۳۸۹",
        "شماره کتابشناسی ملی": "۲۶۹۱۱۲۳"
    },
    "2691124": {},
    "2691125": {},
    "2691126": {},
    "2691127": {},
    "2691128": {
        "شناسه  سند": "۲۹۳/۵۲۲۵۲",
        "عنوان": "تعیین مدیرکل ناحیه راه آهن جنوب[سند]",
        "منشا": "استانداری خوزستان",
        "تاریخ /دوره ایجاد": "۱۳۷۲.",
        "مشخصات ظاهری": "۷ برگ.",
        "دامنه و محتوا": "درخواست بلیط راه آن توسط آموزگار برای معالجه مادرش/ تعیین مدیرکل ناحیه راه آهن جنوب.",
        "توصیفگر": "بلیط\nک‍ارک‍ن‍ان دول‍ت\nدرخ‍واس‍ت\nراهآه‍ن شوشتر",
        "مركز نگهداري سند": "آرشيو ملي ايران",
        "شناسه سند": "۲۹۳/۵۲۲۵۲"
    },
    "2691129": {},
    "2691130": {},
    "2691131": {},
    "2691132": {
        "وضعیت نمایه سازی": "اطلاعات ثبت",
        "شماره کتابشناسی ملی": "۲۶۹۱۱۳۲",
        "شماره واسپاری قانونی": "۶۱۴۱ و",
        "عنوان و  نام پديدآور": "سرزمین مادری [نوار موسیقی]/روزبه",
        "وضعيت نشر": "[تهران]: آوای باربد،  ۱۳۸۲",
        "مشخصات ظاهری": "۱ نوار کاست (ح. '۶۰): با کلام"
    },
    "2691133": {},
    "2691134": {},
    "2691135": {
        "سرشناسه": "ت‍ی‍م‍وری، م‍ح‍م‍دب‍اق‍ر، ۱۳۴۷ -",
        "عنوان و نام پديدآور": "پندارهای صادقانه [کتاب]/ محمدباقر تیموری(تشنه).",
        "مشخصات نشر": "تهران : نشر شیداسب، ۱۳۹۰.",
        "مشخصات ظاهری": "۸۰ص.؛ ۹/۵×۱۹/۵سم.",
        "شابک": "978- 600- 6586-33-5",
        "وضعیت فهرست نویسی": "فیپا",
        "موضوع": "کلمات قصار",
        "رده بندی کنگره": "PN۶۰۹۵/ف۲ت۹۷ ۱۳۹۰",
        "رده بندی دیویی": "۸۰۸/۸۸۲",
        "شماره کتابشناسی ملی": " ۲۶۹۱۱۳۵"
    },
    "2691136": {
        "سرشناسه": "ستاد تبلیغات جنگ",
        "عنوان و نام پديدآور": "تلاشی در تصویر فرهنگ جبهه [کتاب]/ س‍ت‍اد ت‍ب‍ل‍ی‍غ‍ات ج‍ن‍گ.",
        "وضعيت ويراست": "[ویراست ۲]",
        "مشخصات نشر": " تهران: شرکت انتشارات علمی و فرهنگی: ستاد تبلیغات جنگ،  ۱۳۹۰.",
        "مشخصات ظاهری": "۱۶۰، ۱۰ ص.: مصور، عکس.؛ ۲۲ × ۲۹ سم.",
        "شابک": "978-600-121-290-1",
        "يادداشت": "ویراست قبلی: س‍ت‍اد ت‍ب‍ل‍ی‍غ‍ات ج‍ن‍گ: س‍ازم‍ان ان‍ت‍ش‍ارات و آم‍وزش ان‍ق‍لاب اس‍لام‍ی، ۱۳۶۲.",
        "موضوع": "جنگ ایران و عراق، ۱۳۵۹ - ۱۳۶۷ -- عکسها",
        "شناسه افزوده": "شرکت انتشارات علمی و فرهنگی",
        "رده بندی کنگره": "DSR۱۶۰۳/س۲ت۸ ۱۳۹۰",
        "رده بندی دیویی": "۹۵۵/۰۸۴۳۰۲۲۲",
        "شماره کتابشناسی ملی": " ۲۶۹۱۱۳۶"
    },
    "2691137": {
        "سرشناسه": "ترکمانی، محمد، ۱۳۳۹ -",
        "عنوان و نام پديدآور": "تئللی تیکان شعر توپلوسو/ محمد ترکمانی.",
        "مشخصات نشر": "ارومیه: بوتا، ۱۳۹۱.",
        "مشخصات ظاهری": "۱۰۵ص.",
        "فروست": "بوتا نشر؛ ۶۴. شعر؛ ۱۱.",
        "شابک": "۳۵۰۰۰ ریال: 978-600-6039-32-9",
        "وضعیت فهرست نویسی": "فیپا",
        "يادداشت": "ترکی.",
        "موضوع": "شعر ترکی آذربایجانی -- ایران -- قرن ۱۴",
        "رده بندی کنگره": "PL۳۱۴/ت۴۳ت۹ ۱۳۹۱",
        "رده بندی دیویی": "۸۹۴/۳۶۱۱",
        "شماره کتابشناسی ملی": "۲۶۹۱۱۳۷"
    },
    "2691138": {
        "وضعیت نمایه سازی": "اطلاعات ثبت",
        "شماره کتابشناسی ملی": "۲۶۹۱۱۳۸",
        "عنوان و  نام پديدآور": "یا حجه بن الحسن العسگری [کارت]",
        "وضعيت نشر": " تهران:  گلستان کوثر،   [××۱۳].",
        "مشخصات ظاهری": " ۱کارت:  رنگی؛ ۱۶×۱۲س م. (تاشده۸×۱۲س م. )",
        "يادداشت": "(صالح:۱۹۰)",
        "خلاصه": " گلهای رز صورتی"
    },
    "2691139": {
        "سرشناسه": "فیحانی، ماجده، ۱۳۷۱ -",
        "عنوان و نام پديدآور": "میرانه [کتاب]/ماجده فیحانی.",
        "مشخصات نشر": "خرمشهر: اثرآفرین، ۱۳۹۱.",
        "مشخصات ظاهری": "۶۶ص.؛ ۱۴/۵×۲۱سم.",
        "شابک": "978-600-92201-3-7",
        "وضعیت فهرست نویسی": "فاپا",
        "موضوع": "داستانهای فارسی -- قرن ۱۴",
        "رده بندی کنگره": "PIR۸۱۶۹/ی۲۸م۹ ۱۳۹۱",
        "رده بندی دیویی": "۸فا۳/۶۲",
        "شماره کتابشناسی ملی": " ۲۶۹۱۱۳۹"
    },
    "2691140": {
        "شماره مدرک": "۲۶۹۱۱۴۰",
        "محل نگهداري": "آرشيو ملي ايران",
        "شماره بازیابی": "۳۱۱/۲۵/۲۴۲۸",
        "منشاء": "سازمان شاهنشاهی خدمات اجتماعی\nImperial Organization for Social Services",
        "عنوان و  نام پديدآور": "[شاپور بهرامی و هرمز قریب در جشن نوروز وزارت امورخارجه][عکس]",
        "وضعيت توليد/ نشر": " [تهران،۱۳۵۳].",
        "مشخصات ظاهری": "۱عکس: سیاه و سفید؛ ۲۰×۲۵سم.",
        "يادداشت": "یادداشت پشت عکس: نوروز ۱۳۵۳ وزارت امور خارجه. عکس نیاز به مرمت دارد.",
        "چکيده": "شاپور بهرامی به همراه هرمز قریب ریاست کل تشریفات دربار در ساختمان وزارت امورخارجه.",
        "توصیفگر": "بهرامی، شاپور، ۱۳۰۲ -     \nقریب، هرمز، ۱۲۹۴ -      ایران. وزارت امور خارجه دولتمردان",
        "دسترسي و محل الکترونيکي": " Ø¢Ø¯Ø±Ø³ Ø§ÙÚ©ØªØ±ÙÙÛÚ©Û ÙÙØ¨Ø¹ "
    },
    "2691141": {
        "شماره کتابشناسی ملی": "۲۶۹۱۱۴۱",
        "عنوان و  نام پديدآور": "دبیر خانه  اسناد اهدائی و خریداری و وظایف آن [بروشور]",
        "وضعیت نشر": "تهران: سازمان اسناد و کتابخانه ملی جمهوری اسلامی ایران،  ۱۳۴۹.",
        "وضعیت فهرست نویسی": "اطلاعات ثبت"
    },
    "2691142": {},
    "2691143": {
        "سرشناسه": "گیلبرت، ایان، ۱۹۶۵ -     م.\nGilbert, Ian",
        "عنوان و نام پديدآور": "Why do I need a teacher when I’ve got Google?[Book]: the essential guide to the big issues for every 21st century teacher/ Ian Gilbert.",
        "مشخصات نشر": "London ; New York, NY: Routledge،  2011= 1390.",
        "مشخصات ظاهری": "x ،۲۲۰ص.: مصور.",
        "شابک": "978-0-415-46833-6",
        "يادداشت": "انگلیسی.",
        "یادداشت": "کتابنامه: ص.[۲۰۵]- ۲۱۰. نمایه.",
        "آوانویسی عنوان": "وای دو...",
        "موضوع": "تدریس آموزش و پرورش  -- هدفها و نقشها رویدادهای جاری",
        "رده بندی کنگره": "LB۱۰۲۵/۳/گ۹و۲ ۱۳۹۹",
        "رده بندی دیویی": "۳۷۱/۱۰۲",
        "شماره کتابشناسی ملی": "۲۶۹۱۱۴۳"
    },
    "2691144": {
        "سرشناسه": "زمانزاده، مهدی، ۱۳۶۳ -، گردآورنده",
        "عنوان و نام پديدآور": "آزمونهای کاربردی اقتصاد مدیریت: نمونه سوالات ادوار گذشته به همراه پاسخ تشریحی/ مولفان مهدی زمانزاده٬ رعنا حسینی.",
        "مشخصات نشر": "تهران: پاییزه فردا٬ ۱۳۹۰.",
        "مشخصات ظاهری": "۱۰۴ص.: مصور٬ جدول٬ نمودار؛ ۱۴×۲۱ سم.",
        "فروست": "... سری کتابهای کمکآموزشی گام ۲.",
        "شابک": "۳۰۰۰۰ ریال978-600-6494-80-7 :",
        "وضعیت فهرست نویسی": "فیپا",
        "موضوع": "دانشگاهها و مدارس عالی -- ایران -- آزمونها\nاقتصاد مدیریت  -- آزمونها و تمرینها (عالی) \nآزمون دورههای تحصیلات تکمیلی -- ایران",
        "شناسه افزوده": "حسینی، رعنا، ۱۳۶۸ -، گردآورنده",
        "رده بندی کنگره": "LB۲۳۵۳/ز۷۸۶آ۴۴۶ ۱۳۹۰",
        "رده بندی دیویی": "۳۷۸/۱۶۶۴",
        "شماره کتابشناسی ملی": "۲۶۹۱۱۴۴",
        "اطلاعات رکورد کتابشناسی": "فیپا"
    },
    "2691145": {},
    "2691146": {},
    "2691147": {},
    "2691148": {},
    "2691149": {
        "عنوان و  نام پديدآور": "کلهر [پیایند: روزنامه]",
        "مشخصات نشر": "کرمانشاه: [بینا]،  ۱۳۹۰ -",
        "فاصله انتشار": "هفتگي",
        "يادداشت": "صاحب امتیاز و مدیرمسئول: مژگان غیاثوندیان",
        "شماره کتابشناسی ملی": "۲۶۹۱۱۴۹",
        "زبان اثر": "فارسی"
    },
    "2691150": {},
    "2691151": {},
    "2691152": {},
    "2691153": {
        "سرشناسه": "قلیپور، حسین، ۱۳۵۳ -",
        "عنوان و نام پديدآور": "دایرهالمعارف قطعات الکترونیک/ تالیف حسین قلیپور.",
        "مشخصات نشر": "تهران: فرهنگ متین: کتاب پدیده: پیشگامان اندیشه، ۱۳۸۹.",
        "مشخصات ظاهری": "۲۸۸ ص.: مصور (بخشی رنگی)، جدول.",
        "شابک": "۷۰۰۰۰ ریال978-600-5825-00-8 :",
        "يادداشت": "چاپ سوم. چاپ قبلی: فرهنگ متین: کتاب پدیده: پیشگامان اندیشه، ۱۳۸۹.( ۳۰۴ ص) عنوان روی جلد: دایرهالمعارف قطعات الکترونیک: تحلیل ۲۴ گروه اصلی و ۶۵۰ زیرگروه مهم شامل: نحوه عملکرد ... .",
        "یادداشت": "کتابنامه: ص. ۲۸۶.",
        "عنوان روی جلد": "دایرهالمعارف قطعات الکترونیک: تحلیل ۲۴ گروه اصلی و ۶۵۰ زیرگروه مهم شامل: نحوه عملکرد ... .",
        "موضوع": "ابزار و تجهیزات الکترونیکی -- دایرهالمعارفها\nابزار و تجهیزات الکترونیکی -- راهنماها",
        "رده بندی کنگره": "TK۷۸۷۸/۴/ق۸د۲ ۱۳۸۹الف",
        "رده بندی دیویی": "۶۲۱/۳۸۱۰۳",
        "شماره کتابشناسی ملی": "۲۶۹۱۱۵۳"
    },
    "2691154": {},
    "2691155": {},
    "2691156": {
        "وضعیت نمایه سازی": "اطلاعات ثبت",
        "شماره کتابشناسی ملی": "۲۶۹۱۱۵۶",
        "عنوان و  نام پديدآور": "اللهم صل علی حجتک فی ارضک [کارت]",
        "وضعيت نشر": " تهران:  گلستان کوثر،   [××۱۳].",
        "مشخصات ظاهری": " ۱کارت:  رنگی؛ ۱۲×۱۶س م. (تاشده۸×۱۶س م. )",
        "يادداشت": "(صالح:۱۸۷)",
        "خلاصه": " عنوان در کنار گلهای ریز سفید و صورتی"
    },
    "2691157": {
        "2691157": "﻿محدودیت دسترسی در نمایش اطلاعات"
    },
    "2691158": {},
    "2691159": {
        "سرشناسه": "راس، کیت، ۱۹۴۴ -     م.\nRoss, Keith",
        "عنوان و نام پديدآور": "Teaching secondary science : constructing meaning and developing understanding[Book]/ Keith Ross, Liz Lakin and Janet McKechnie.",
        "وضعيت ويراست": "ویراست سوم.",
        "مشخصات نشر": "London; New York: Routledge،  2010= 1389.",
        "مشخصات ظاهری": "xv ،۲۴۶ص.: مصور.",
        "شابک": "978-0-415-46886-2",
        "يادداشت": "انگلیسی.",
        "یادداشت": "کتابنامه. نمایه.",
        "آوانویسی عنوان": "تیچینگ...",
        "موضوع": "علوم -- راهنمای آموزشی (متوسطه)",
        "شناسه افزوده": "لیکین، لیز Lakin, Liz مکچنی، جانت McKechnie, Janet",
        "رده بندی کنگره": "Q۱۸۱/ر۲ت۹ ۱۳۸۹",
        "رده بندی دیویی": " ۵۱۰/۷۱۲",
        "شماره کتابشناسی ملی": "۲۶۹۱۱۵۹"
    },
    "2691160": {},
    "2691161": {
        "سرشناسه": "هال، جی. کی.\nHall, G. K.",
        "عنوان و نام پديدآور": "Annual bibliography of modern art 2001-2002[Book]/ G. K. Hall.",
        "مشخصات نشر": "New haven: Thomson، 2003= 1382.",
        "مشخصات ظاهری": "۳۵۱ص.",
        "شابک": "0-7838-9787-1",
        "يادداشت": "انگلیسی.",
        "آوانویسی عنوان": "انوال...",
        "موضوع": "هنرهای نوین -- قرن ۲۰م.",
        "رده بندی کنگره": "NX۴۵۶/ھ۲الف۸  ۱۳۸۲",
        "رده بندی دیویی": "۷۰۰/۹۰۴",
        "شماره کتابشناسی ملی": "۲۶۹۱۱۶۱"
    },
    "2691162": {},
    "2691163": {},
    "2691164": {},
    "2691165": {},
    "2691166": {},
    "2691167": {},
    "2691168": {},
    "2691169": {},
    "2691170": {},
    "2691171": {
        "شماره کتابشناسی ملی": " ۲۶۹۱۱۷۱",
        "عنوان و  نام پديدآور": "کتابخانه نابینایان و کم بینایان [بروشور]",
        "وضعیت نشر": "تهران: سازمان اسناد و کتابخانه ملی جمهوری اسلامی ایران،  ۱۳۷۳.",
        "وضعیت فهرست نویسی": "اطلاعات ثبت"
    },
    "2691172": {},
    "2691173": {},
    "2691174": {
        "عنوان و  نام پديدآور": "مبشر [پیایند: روزنامه]",
        "مشخصات نشر": "کرمانشاه: [بینا]،  ۱۳۹۰ -",
        "فاصله انتشار": "هفتگي",
        "يادداشت": "فهرستنویسی بر اساس سال۳ شماره۱۰۳ سال۱۳۹۰. صاحب امتیاز و مدیرمسئول: احسان احسانی",
        "شماره کتابشناسی ملی": "۲۶۹۱۱۷۴",
        "زبان اثر": "فارسی"
    },
    "2691175": {
        "وضعیت نمایه سازی": "اطلاعات ثبت",
        "شماره کتابشناسی ملی": "۲۶۹۱۱۷۵",
        "شماره واسپاری قانونی": "۵۷۶۶ و",
        "عنوان و  نام پديدآور": "ترانهها و خاطرات ( ۱ ) [نوار موسیقی]/رحیم مطلوبی ( فرهنگ )",
        "وضعيت نشر": "[تهران]: هم آواز آهنگ،  [××۱۳]",
        "مشخصات ظاهری": "۱ نوار کاست (ح. '۶۰): بی کلام"
    },
    "2691176": {
        "دسترسي به فايل تمام متن": "برای دستیابی به فایل تمام متن منبع، به \"تالار منابع رقمی\" مراجعه فرمایید. Ø¢Ø¯Ø±Ø³ Ø§ÙÚ©ØªØ±ÙÙÛÚ©Û ÙÙØ¨Ø¹ ",
        "شماره بازیابی": "۵۱-۷۰۳۱۹",
        "شماره کتابشناسی ملی": "۲۶۹۱۱۷۶",
        "پدیدآور": "لسانی، لیدا",
        "عنوان و  نام پديدآور": "شناساندن رنگ از طریق زیردستهای مختلف و ایجاد طرحهای چاپی قابل درک برای افراد روشندل [پ‍ای‍انن‍ام‍ه]/ دانشجو لیدا لسانی؛ استادان راهنما ابوالفضل داودیرکنآبادی، نوید خالصی؛ استادان مشاور محمدمهدی کریمنژاد، سالار ظهوری.",
        "مقطع و رشته تحصیلی": "(کارشناسی): طراحی پارچه و لباس، گرایش طراحی چاپ پارچه.",
        "محل و سال اخذ مدرک": "، ۱۳۸۹.",
        "نام دانشگاه/ پژوهشگاه": "دانشگاه آزاد اسلامی، واحد یزد، دانشکده هنر، گروه طراحی پارچه و لباس.",
        "مشخصات نشر": "۱۳۸۹.",
        "مشخصات ظاهری": "ح، [۹۸] ورق: مصور (بخشیرنگی)، جدول، عکس، نمودار (رنگی)، پرسشنامه.",
        "يادداشت": "چکیده: فارسی- انگلیسی. در انتهای پایاننامه ۱۷ ورق مربوط به مقاله پژوهشگر است.",
        "یادداشت": "کتابنامه: ص. ۸۰-۸۱.",
        "شناسه افزوده": "داودی رکنآبادی، ابوالفضل، ۱۳۵۱ - ، استاد راهنما خالصی، نوید، استاد راهنما کریمنژاد، محمدمهدی، استاد مشاور ظهوري، سالار، ۱۳۶۴ -، استاد مشاور دانشگاه آزاد اسلامی. واحد یزد. دانشکده هنر. گروه طراحی پارچه و لباس",
        "توصیفگر": "ن‍ا ب‍ی‍ن‍ای‍ان\nلامسه\nناهمواری رویهها\nپارچه\nرنگ درمانی"
    },
    "2691177": {
        "عنوان و نام پديدآور": "The future of Asian trade and growth[Book]: economic development with the emergence of China/ edited by Linda Yueh.",
        "مشخصات نشر": "London ;New york: Routledge،  2010= 1389.",
        "مشخصات ظاهری": "xxii ،۴۴۲ص.",
        "فروست": "Routledge studies in the growth economies of Asia; 92",
        "شابک": "978-0-415-36811-7",
        "يادداشت": "انگلیسی.",
        "یادداشت": "کتابنامه. نمایه.",
        "آوانویسی عنوان": "فیوچر ...",
        "موضوع": "آسیا--روابط اقتصادی چین -- بازرگانی آسیا--بازرگانی چین -- سیاست اقتصادی آسیا--سیاست اقتصادی",
        "شناسه افزوده": "یوئه، لیندا یی-جوانگ، ویراستار Yueh, Linda Y. (Linda Yi-Chuang)",
        "رده بندی کنگره": "HF۱۶۰۴/ف۹ ۱۳۸۹",
        "رده بندی دیویی": "۳۸۲/۰۹۵",
        "شماره کتابشناسی ملی": "۲۶۹۱۱۷۷"
    },
    "2691178": {},
    "2691179": {
        "سرشناسه": "باقری، منیره، ۱۳۶۲ -، گردآورنده",
        "عنوان و نام پديدآور": "آزمونهای کاربردی تاریخ بیزانس: نمونه سوالات ادوار گذشته به همراه پاسخ تشریحی/ مولفان منیره باقری٬ مونا باقری.",
        "مشخصات نشر": "تهران: پاییزه فردا٬ ۱۳۹۰.",
        "مشخصات ظاهری": "۱۰۴ص.: جدول؛ ۱۴×۲۱ سم.",
        "فروست": "... سری کتابهای کمکآموزشی گام ۲.",
        "شابک": "۳۰۰۰۰ ریال978-600-6494-79-1 :",
        "وضعیت فهرست نویسی": "فیپا",
        "موضوع": "دانشگاهها و مدارس عالی -- ایران -- آزمونها\nآزمون دورههای تحصیلات تکمیلی -- ایران بیزانس، امپراتوری -- تاریخ -- آزمونها و تمرینها (عالی)",
        "شناسه افزوده": "باقری، مونا، ۱۳۶۵ -، گردآورنده",
        "رده بندی کنگره": "LB۲۳۵۳/ب۱۸۲۷آ۳۴ ۱۳۹۰",
        "رده بندی دیویی": "۳۷۸/۱۶۶۴",
        "شماره کتابشناسی ملی": "۲۶۹۱۱۷۹",
        "اطلاعات رکورد کتابشناسی": "فیپا"
    },
    "2691180": {},
    "2691181": {
        "سرشناسه": "ه‍ول‍م‍ن، ج‍ک ف‍ی‍ل‍ی‍پ\nHolman, J. P. (Jack Philip)",
        "عنوان و نام پديدآور": "انتقال حرارت [کتاب]/ ج‍یپی ه‍ول‍م‍ن ؛ ترجمه م‍ل‍کزاده، ک‍اش‍ان‍یح‍صار.",
        "مشخصات نشر": "مشهد : نشر نما: جهان فردا،  ۱۳۹۱.",
        "مشخصات ظاهری": "۷۵۷  ص.: مصور،جدول.",
        "شابک": "۲۵۰۰۰۰ ریال978-600-217-021-7 :",
        "وضعیت فهرست نویسی": "فاپا",
        "يادداشت": "عنوان اصلی: .Heat transfer, 10th ed, 2010 کتاب حاضر در سالهای مختلف توسط مترجمان و ناشران متفاوت منتشر شده است. چاپ هفدهم.",
        "یادداشت": "واژهنامه.",
        "موضوع": "گرما -- انتقال",
        "شناسه افزوده": "م‍ل‍کزاده، غ‍لام‍رض‍ا، ۱۳۳۹ -، مترجم ک‍اش‍ان‍ی ح‍ص‍ار، م‍ح‍م‍دح‍س‍ی‍ن، ۱۳۳۶ - ، مترجم",
        "رده بندی کنگره": "QC۳۲۰/ھ۹الف۸ ۱۳۹۱",
        "رده بندی دیویی": "۶۲۱/۴۰۲۲",
        "شماره کتابشناسی ملی": " ۲۶۹۱۱۸۱"
    },
    "2691182": {
        "سرشناسه": "نیکبخش، حمیدرضا، ۱۳۶۷ -",
        "عنوان و نام پديدآور": "رازهای جنگ جهانی دوم: چگونه جنگ جهانی دوم بر آلمان تحمیل شد/ مولف حمیدرضا نیکبخش.",
        "مشخصات نشر": "اهواز: ترآوا، ۱۳۹۱.",
        "مشخصات ظاهری": "۱۵۲ ص.: مصور، جدول؛ ۱۴ × ۲۱ سم.",
        "شابک": "978-600-6349-44-2",
        "وضعیت فهرست نویسی": "فیپا",
        "یادداشت": "کتابنامه: ص. [۱۴۱ - ۱۵۲].",
        "عنوان دیگر": "چگونه جنگ جهانی دوم بر آلمان تحمیل شد.",
        "موضوع": "جنگ جهانی دوم، ۱۹۳۹-۱۹۴۵م.",
        "رده بندی کنگره": "D۷۴۳/ن۹ر۲ ۱۳۹۱",
        "رده بندی دیویی": "۹۴۰/۵۳",
        "شماره کتابشناسی ملی": "۲۶۹۱۱۸۲"
    },
    "2691183": {
        "وضعیت نمایه سازی": "اطلاعات ثبت",
        "شماره کتابشناسی ملی": "۲۶۹۱۱۸۳",
        "عنوان و  نام پديدآور": "السلام علی المهدی المنتظر [کارت]",
        "وضعيت نشر": " تهران:  گلستان کوثر،   [××۱۳].",
        "مشخصات ظاهری": "۱کارت:  رنگی؛ ۱۲×۱۶س م. (تاشده۸×۱۲س م. )",
        "يادداشت": "(صالح:۲۳۷)",
        "خلاصه": " عنوان در بالای گل رز صورتی"
    },
    "2691184": {
        "سرشناسه": "میور، نانسی، ۱۹۵۴ -     م.\nMuir, Nancy",
        "عنوان و نام پديدآور": "آموزش تصویری کامپیوترهای لپ تاپ/ امیراحسان رضایی.",
        "مشخصات نشر": "تهران: مهرگان قلم، ۱۳۹۱.",
        "مشخصات ظاهری": "۲۶۰ ص.: مصور، جدول.",
        "شابک": "۶۰۰۰۰ریال978-600-6236-18-6 :",
        "وضعیت فهرست نویسی": "فاپا",
        "يادداشت": "عنوان اصلی: Teach Yourself VISUALLY laptops, c2008.",
        "موضوع": "کامپیوترهای لپتاپ\nکامپیوترهای قابل حمل",
        "شناسه افزوده": "رضائی، امیراحسان، ۱۳۵۹ -، مترجم",
        "رده بندی کنگره": "QA۷۶/۵/م۸۶آ۷۴ ۱۳۹۱",
        "رده بندی دیویی": "۰۰۴/۱۶",
        "شماره کتابشناسی ملی": "۲۶۹۱۱۸۴",
        "اطلاعات رکورد کتابشناسی": "فاپا"
    },
    "2691185": {},
    "2691186": {},
    "2691187": {
        "2691187": "﻿محدودیت دسترسی در نمایش اطلاعات"
    },
    "2691188": {
        "سرشناسه": "ان‍س‍ان‍ی، ش‍ه‍لا، ۱۳۲۵ -     ، اقتباسکننده",
        "عنوان قراردادی": "شاهنامه. برگزیده",
        "عنوان و نام پديدآور": "داستانهای شاهنامه: از کیومرث تا کیخسرو/ بازآفرینی شهلا انسانی.",
        "مشخصات نشر": "تهران: سمیر، ۱۳۹۶.",
        "مشخصات ظاهری": "۵۰۱ص.",
        "شابک": "دوره978-964-220-310-9:  ؛  ۳۵۰۰۰۰ ریال: 978-964-220-155-6",
        "وضعیت فهرست نویسی": "فاپا (چاپ سوم)",
        "يادداشت": "کتاب حاضر اقتباسی از '' شاهنامه فردوسی '' است. چاپ سوم.",
        "موضوع": "فردوسی، ابوالقاسم، ۳۲۹ - ۴۱۶؟ ق . شاهنامه -- اقتباسها Ferdowsi, Abolqasem. Shahnameh -- Adaptations داستانهای فارسی -- قرن ۱۴\nPersian fiction -- 20th century",
        "شناسه افزوده": "فردوسی، ابوالقاسم، ۳۲۹ - ۴۱۶؟ ق . شاهنامه. برگزیده",
        "رده بندی کنگره": "PIR۷۹۶۲ /ن۵د۲ ۱۳۹۶",
        "رده بندی دیویی": "۸فا۳/۶۲",
        "شماره کتابشناسی ملی": "۲۶۹۱۱۸۸",
        "اطلاعات رکورد کتابشناسی": "فاپا"
    },
    "2691189": {
        "سرشناسه": "ص‍داق‍تن‍ژاد، ج‍م‍ش‍ی‍د، ۱۳۲۶ -",
        "عنوان و نام پديدآور": "تیسفون در آتش: شاپور دوم، معمار سلسله ساسانی/ جمشید صداقتنژاد.",
        "مشخصات نشر": "تهران: سمیر، ۱۳۹۸.",
        "مشخصات ظاهری": "۶۱۶ص.",
        "فروست": "ایران در زمان ساسانیان.",
        "شابک": "۹۵۰۰۰۰ ریال978-964-220-150-1 :",
        "وضعیت فهرست نویسی": "فاپا (چاپ دوم)",
        "يادداشت": "پشت جلد به انگلیسی:  Jamshid Sedaghat nejad. Tisfoon in fire: Shapoor II, the architect of ... . چاپ دوم.",
        "یادداشت": "کتابنامه: ص.۶۱۴ - ۶۱۶.",
        "عنوان دیگر": "شاپور دوم، معمار سلسله ساسانی.",
        "موضوع": "ش‍اپ‍ور س‍اس‍ان‍ی دوم، ش‍اه ای‍ران،      - ۳۷۹م. داستانهای فارسی -- قرن ۱۴\nPersian fiction -- 20th century",
        "رده بندی کنگره": "PIR۸۱۳۱ /د۲۵ت۹۳ ۱۳۹۸",
        "رده بندی دیویی": "۸فا۳/۶۲",
        "شماره کتابشناسی ملی": "۲۶۹۱۱۸۹",
        "اطلاعات رکورد کتابشناسی": "فاپا"
    },
    "2691190": {},
    "2691191": {},
    "2691192": {
        "شماره مدرک": " ۲۶۹۱۱۹۲",
        "محل نگهداري": "آرشيو ملي ايران",
        "شماره بازیابی": "۳۱۱/۲۵/۲۴۲۷",
        "منشاء": "سازمان شاهنشاهی خدمات اجتماعی\nImperial Organization for Social Services",
        "عنوان و  نام پديدآور": "[منوچهر اقبال][عکس]",
        "وضعيت توليد/ نشر": "[۱۳۵۰-۱۳۴۰؟].",
        "مشخصات ظاهری": "۱عکس: سیاه و سفید؛ ۲۱×۱۶سم.",
        "چکيده": "منوچهر اقبال در حال روبوسی با یکی از مقامات مملکتی.",
        "توصیفگر": "اق‍ب‍ال، م‍ن‍وچ‍ه‍ر، ۱۲۸۸ - ۱۳۵۶. وزی‍ران\nدولتمردان",
        "دسترسي و محل الکترونيکي": " Ø¢Ø¯Ø±Ø³ Ø§ÙÚ©ØªØ±ÙÙÛÚ©Û ÙÙØ¨Ø¹ "
    },
    "2691193": {},
    "2691194": {},
    "2691195": {},
    "2691196": {},
    "2691197": {},
    "2691198": {},
    "2691199": {},
    "2691200": {}
}