{
    "3158401": {
        "شناسه  سند": "۲۴۰/۵۷۱۱۹",
        "شناسه بازيابي": "۱۳/۱/۵۷۱۱۹",
        "عنوان": "طلب حافظالقاضی بابت هزینه فیلم ورود ولیعهد به عراق [سند]",
        "منشا": "ایران. وزارت امور اقتصادی و دارایی",
        "تاریخ /دوره ایجاد": "۱۳۱۸.",
        "مشخصات ظاهری": "۱۶ برگ.",
        "دامنه و محتوا": "مکاتبات وزارت خارجه با وزارت دارایی راجع به پرداخت مطالبات آقای حافظالقاضی از بابت هزینه فیلم مسافرت ولیعهد ایران به عراق.",
        "توصیفگر": "م‍ح‍م‍درض‍ا پ‍ه‍ل‍وی، ش‍اه ای‍ران، ۱۲۹۸ - ۱۳۵۹. ایران. وزارت دارایی\nایران. وزارت امور خارجه\nIranMinistry of Foreign Affairs Islamic Republic of Iran دی‍ون\nه‍زی‍ن‍ه ه‍ا\nف‍ی‍ل‍مه‍ا\nس‍ف‍ارتخ‍ان‍هه‍ا\nه‍ی‍ات دول‍ت\nس‍ف‍را\nم‍س‍اف‍رت\nق‍ی‍م‍ت ه‍ا\nت‍ص‍وی‍بن‍ام‍هها عراق\nتهران",
        "مركز نگهداري سند": "آرشيو ملي ايران",
        "شناسه سند": "۲۴۰/۵۷۱۱۹"
    },
    "3158402": {
        "شناسه  سند": "۲۴۰/۱۰۲۳۳۷",
        "شناسه بازيابي": "۱۳/۱/۱۰۲۳۳۷",
        "عنوان": "تامین هزینه فرشهای اهدائی به مقامات سیاسی پاکستان در کنفرانس اسلامی کراچی [سند]",
        "سطح استاندارد": "پرونده",
        "منشا": "ایران. وزارت امور اقتصادی و دارایی",
        "تاریخ /دوره ایجاد": "۱۳۳۰.",
        "مشخصات ظاهری": "۱۲ برگ.",
        "دامنه و محتوا": "دستورالعمل وزارت دارایی به وزارت اقتصاد ملی جهت رسیدگی به موضوع تامین هزینه بهای دو تخته فرش اهداء شده به مقامات سیاسی پاکستان توسط نمایندگان هیات اعزامی ایران در کنفرانس اسلامی کراچی.",
        "توصیفگر": "قالی\nگ‍رده‍م‍ای‍ی ه‍ا\nن‍م‍ای‍ش‍گ‍اه ه‍ا\nاع‍ت‍ب‍ارات\nه‍دای‍ا\nم‍ام‍وران س‍ی‍اس‍ی\nکشورهای اسلامی ایران\nپاکستان",
        "مركز نگهداري سند": "آرشيو ملي ايران",
        "شناسه سند": "۲۴۰/۱۰۲۳۳۷"
    },
    "3158403": {},
    "3158404": {},
    "3158405": {},
    "3158406": {},
    "3158407": {},
    "3158408": {
        "شناسه  سند": "۲۴۰/۱۰۲۳۳۶",
        "شناسه بازيابي": "۱۳/۱/۱۰۲۳۳۶",
        "عنوان": "تامین هزینه مامورین دولت و دانشجویان [سند]",
        "سطح استاندارد": "پرونده",
        "منشا": "ایران. وزارت امور اقتصادی و دارایی",
        "تاریخ /دوره ایجاد": "۱۳۳۱.",
        "مشخصات ظاهری": "۲ برگ.",
        "دامنه و محتوا": "درخواست وزارت دارایی از سازمان برنامه و بودجه برای رسیدگی درخصوص هزینه نمودن مارکهای حاصله از فروش برخی از لوازم غیرقابل مصرف کارخانجات آلمانی جهت پرداخت مخارج مامورین دولت و دانشجویان.",
        "توصیفگر": "ایران. وزارت دارایی\nسازمان برنامه و بودجه ک‍ارک‍ن‍ان دول‍ت\nدان‍ش‍ج‍وی‍ان\nه‍زی‍ن‍ه ه‍ای اداری\nم‍ام‍وری‍ت\nت‍ح‍ص‍ی‍ل در خ‍ارج از ک‍ش‍ور\nارز آلمان ",
        "مركز نگهداري سند": "آرشيو ملي ايران",
        "شناسه سند": "۲۴۰/۱۰۲۳۳۶"
    },
    "3158409": {
        "شناسه  سند": "۲۴۰/۵۷۱۲۰",
        "شناسه بازيابي": "۱۳/۱/۵۷۱۲۰",
        "عنوان": "بررسی اراضی دیلم و فروش آن توسط خوانین [سند]",
        "منشا": "ایران. وزارت امور اقتصادی و دارایی",
        "تاریخ /دوره ایجاد": "۱۳۱۰.",
        "مشخصات ظاهری": "۷ برگ.",
        "دامنه و محتوا": "درخواست گزارش از رئیس مالیه بنادر جنوب در خصوص فروش اراضی دیلم و تقاضای قبالجات منطقه برای بررسی صاحبان اصلی آنها برای فروش اراضی منطقه.",
        "توصیفگر": "ایران. وزارت مالیه ملک\nم‍ال‍ک‍ان\nف‍روش\nاراض‍ی ک‍ش‍اورزی بندر دیلم\nبوشهر",
        "مركز نگهداري سند": "آرشيو ملي ايران",
        "شناسه سند": "۲۴۰/۵۷۱۲۰"
    },
    "3158410": {
        "مرکز نگهدارنده نسخه": "کتابخانه ملی",
        "شماره بازیابی نسخه": "۵-۱۹۹۹۲/۶",
        "شماره هاي شناسايي دیگر": "۱۹۹۹۲/۶",
        "عنوان و  نام پديدآور": "رساله در اثبات وجود خدا[نسخه خطی]",
        "وضعیت استنساخ": "، احتمالا قرن ۱۲ق.",
        "آغاز ، انجام ، انجامه": "آغاز:[افتاده] : صفه الواجب علیه و بطلانه اوضح من ان یوضح ....\nانجام:.... و العشاء فی المورد و المذهب والله ولی الاعتصام فی الافتتاح و الاختتام",
        "مشخصات ظاهري": "۳۶ر -   ۶۱ر (۷۵ برگ)، ۳۱ سطر حمایلی، اندازه متن: ۸۵×۱۸۵؛ قطع: ۱۵۵×۲۵۵",
        "يادداشت مشخصات ظاهری": "نوع و درجه خط:نسخ خوش\nنوع کاغذ:ترمه",
        "خصوصيات نسخه موجود": "حواشی اوراق:حاشیه هایی با نشان (منه) دارد و در بعضی از آنها از دوانی نقل شده است",
        "معرفی نسخه": "رساله ای کلامی در اثبات وجود باری تعالی ، از آغاز افتادگی دارد و دانشته نشد از کیست ، در آن از فخر رازی و جلال الدین دوانی یاد شده است ، ظاهرا به همان قلم رساله قبل نوشته شده است",
        "یاداشت تملک و سجع مهر": "شکل  و سجع مهر:مهر (عبد الوهاب فرید تنکابنی) در چند جای نسخه",
        "توضیحات نسخه": "نسخه بررسی شده .",
        "يادداشت کلی": "زبان : عربی",
        "منبع تهیه": "خریداری از محمد رضا فرید تنکابنی درتاریخ ۲۳/۲/۸۵",
        "صحافي شده با :": "درر الدقائق و درر الحقائق / صدر الدین موفق بن محمد خاصی خوارزمی، احتمالا قرن ۱۰ق.1155052",
        "موضوع": "خدا  -- اثبات -- متون قدیمی تا قرن ۱۴\nعلم ک‍لام-- متون قدیمی تا قرن ۱۴",
        "شناسه افزوده": "ف‍ری‍د ت‍ن‍ک‍اب‍ن‍ی، ع‍ب‍دال‍وه‍اب، ۱۲۸۶-، مالک قبلی فرید تنکابنی،محمدرضا،فروشنده"
    },
    "3158411": {
        "شناسه  سند": "۲۴۰/۱۰۲۳۳۵",
        "شناسه بازيابي": "۱۳/۱/۱۰۲۳۳۵",
        "عنوان": "تامین اتومبیل مورد نیاز ادارات بندر پهلوی و خرمشهر [سند]",
        "سطح استاندارد": "پرونده",
        "منشا": "ایران. وزارت امور اقتصادی و دارایی",
        "تاریخ /دوره ایجاد": "۱۳۳۰.",
        "مشخصات ظاهری": "۸ برگ.",
        "دامنه و محتوا": "رسیدگی وزارت دارایی درخصوص خرید اتومبیلهای مورد نیاز بنگاه کل بنادر و کشتیرانی و نیز خرید اتومبیل برای اداره بندر پهلوی و اداره بندر خرمشهر.",
        "توصیفگر": "سازمان بنادر و کشتیرانی\nایران. وزارت دارایی وس‍ای‍ل ح‍م‍ل و ن‍ق‍ل زم‍ی‍ن‍ی\nک‍ام‍ی‍ونه‍ا\nاع‍ت‍ب‍ارات\nخ‍ری‍د\nات‍وم‍ب‍ی‍له‍ای س‍واری\nب‍ن‍دره‍ا خرمشهر\nبندرانزلی",
        "مركز نگهداري سند": "آرشيو ملي ايران",
        "شناسه سند": "۲۴۰/۱۰۲۳۳۵"
    },
    "3158412": {
        "شناسه  سند": "۲۴۰/۱۰۲۳۳۴",
        "شناسه بازيابي": "۱۳/۱/۱۰۲۳۳۴",
        "عنوان": "مطالبه خسارت از کارگر مؤسسه انحصار دخانیات ایران [سند]",
        "سطح استاندارد": "پرونده",
        "منشا": "ایران. وزارت امور اقتصادی و دارایی",
        "تاریخ /دوره ایجاد": "۱۳۲۰ـ۱۳۲۹.",
        "مشخصات ظاهری": "۵۰ برگ.",
        "دامنه و محتوا": "رسیدگی اداره بازرسی کل وزارت دارایی درخصوص مطالبه خسارت وارده توسط عباس شاداب به موتورسیکلت مؤسسه انحصار دخانیات ایران.",
        "توصیفگر": "ایران. وزارت دارایی\nموسسه انحصار دخانیات ایران وس‍ای‍ل ح‍م‍ل و ن‍ق‍ل زم‍ی‍ن‍ی\nک‍ارگ‍ران\nدخانیات\nب‍ازرس‍ی\nک‍ارک‍ن‍ان دول‍ت\nخسارت",
        "مركز نگهداري سند": "آرشيو ملي ايران",
        "شناسه سند": "۲۴۰/۱۰۲۳۳۴"
    },
    "3158413": {
        "شناسه  سند": "۲۴۰/۱۰۲۳۳۳",
        "شناسه بازيابي": "۱۳/۱/۱۰۲۳۳۳",
        "عنوان": "بازرسی اموال اداره کل املاک وزارت دارایی [سند]",
        "سطح استاندارد": "پرونده",
        "منشا": "ایران. وزارت امور اقتصادی و دارایی",
        "تاریخ /دوره ایجاد": "۱۳۲۶ـ۱۳۲۷.",
        "مشخصات ظاهری": "۱۰ برگ.",
        "دامنه و محتوا": "رسیدگی اداره بازرسی کل وزارت دارایی درخصوص بازرسی از اداره کل املاک و خالصه و آشفتگی وضع اموال ادارات تابعه و لزوم اصلاح امور اداره مزبور.",
        "توصیفگر": "ایران. وزارت دارایی ب‍ازرس‍ی\nام‍وال م‍ن‍ق‍ول",
        "مركز نگهداري سند": "آرشيو ملي ايران",
        "شناسه سند": "۲۴۰/۱۰۲۳۳۳"
    },
    "3158414": {},
    "3158415": {
        "مرکز نگهدارنده نسخه": "کتابخانه ملی",
        "شماره بازیابی نسخه": "۵-۱۹۹۹۲/۷",
        "شماره هاي شناسايي دیگر": "۱۹۹۹۲/۷",
        "سرشناسه": "غ‍زال‍ی، اح‍م‍د ب‍ن م‍ح‍م‍د،      -۵۲۰ق.، پدید آور مشكوك\nع‍ی‍نال‍ق‍ض‍اه، ع‍ب‍دال‍ل‍ه ب‍ن م‍ح‍م‍د، ۴۹۲ - ۵۲۵ ق.، پدید آور مشكوك",
        "عنوان و  نام پديدآور": "رازنامه[نسخه خطی]/ شاید احمد بن محمد غزالی",
        "وضعیت استنساخ": "، ۹۸۱ق.",
        "آغاز ، انجام ، انجامه": "آغاز:سلام الله تعالی علی المجلس الاسمی المنعمی الاقصوی الرضوی الصفوی الکفوی الجمالی الشرفی ....ان هذه تذکره فمن شاء اتخذ الی ربه سبیلا ...اما بعد ا سید الکبراء قولا مطلقا ......\nانجام:... و نعوذ بالله من دعاء لا یسمع و قلب لا یخشع و بطن لا یشبع [کذا] و علم لا ینفع والحمد لله اولا و اخرا ....وعترته الطاهرین\nانجامه:تم بتوفیق الله سبحانه فی سنه ۹۸۱",
        "مشخصات ظاهري": "۶۱ر - ۶۷پ (۷۵ برگ)،   ، ۳۰ سطر حمایلی، اندازه متن: ۸۵×۱۸۰؛ قطع: ۱۵۵×۲۵۵",
        "يادداشت مشخصات ظاهری": "نوع و درجه خط:نسخ خوش\nنوع کاغذ:ترمه",
        "يادداشت استنساخ": "در صفحات ۶۵ - ۷۰ اشعاری به فارسی بصورت چلیپا نوشته شده",
        "معرفی نسخه": "رساله ای عرفانی شامل پند و اندرزهایی با نثری ادبی  به فارسی و عربی همراه با  آیات قرآنی و اشعاری به فارسی و بعضی گفته های حکیمانه بزرگان است که نویسنده، آن را  برای شخصی نوشته  و او را با عبارت (المجلس الاسمی المنعمی الاقصوی الرضوی الصفوی الکفوی الجمالی الشرفی ...) مورد خطاب قرار داده  است.   نامی از مولف و مخاطب در آن نیامده ، ولی در بیشتر منابع  و فهرستها  از این این اثر به عنوان نامهای  از احمد بن محمد غزالی دانسته شده  که آن را برای عین القضات همدانی نوشته است.  میان عین القضات و مراد او شیخ احمد غزالی مکاتبات و نامه نگاریهای متعددی یاد شده  که هفت نامه آن را آقای احمد مجاهد  در ضمن مجموعه آثار فارسی احمد غزالی آورده است.  معروفترین و مفصلترین آنها همین اثر است که آن را در بلاغت و فصاحت و روانی و سلاست کم نطیر دانسته اند.  غزالی کوشیده که  عقاید و مکنونات قلبی خود را با استفاده از آیات و احادیث و اشعار شاعران بیان کند و همچنین از نوادر اقوال و گفتههای حکیمانه  عرفا و حکما و فقها و ادیبان و شعرا و جز آنان بهره ببرد.  نام این اثر به درستی دانسته نیست و در منابع به نامهای گوناگونی چون « عینیه» ، « رازنامه»،  « صلوات شریفه»، « مکتوب الامام الغزالی الی عین القضاة الهمدانی»  یاد شده است و  با نام  « تازیانه سلوک» به چاپ رسیده است. به گفته حسن مشکات طبسی در مقدمه چاپ این اثر، چون این متن بین پیر و مرید به عنوان مراسله رد و بدل شده  نه به عنوان کتاب یا رساله علمی، بعید است که خود نویسنده نامی روی آن گذاشته باشد؛ و اینکه بعضی آن را رساله عینیه نامیدهاند اسمی است که خود آنها به مناسبت نام عین القضات روی آن نهادهاند.  نسخه های متعددی از آن در کتابخانه های ایران نگهداری میشود ؛ نسخهای در کتابخانه آیه الله مرعشی در قم نگهداری میشود که در فهرست  آن کتابخانه(۱۹: ۲۶)  با عنوان  «رساله عینیه»  از غزالی دانسته شده و در  (۱۳ : ۹۰) همان فهرست،  به نام «رازنامه» از مولفی ناشناخته شناسانده شده است .   بر اساس گفته مؤلف درآن که گفته است(و اگر نه آنستی که سینه آن خلاصه عصر .... این تصدیع ندادمی و این رازنامه نگشادمی)  میتوان گفت که «رازنامه»  برای نام آن مناسب باشد.",
        "یاداشت تملک و سجع مهر": "شکل  و سجع مهر:مهر (عبد الوهاب فرید تنکابنی) در چند جای نسخه",
        "توضیحات نسخه": "نسخه بررسی شده .",
        "يادداشت کلی": "زبان : عربی",
        "يادداشت باز تکثير": "این اثر بارها توسط ناشرین مختلف چاپ شده است که از آنها است:  در مجله ارمغان، شماره هشتم، در سال ۱۳۰۶ش؛  به کوشش نصرالله تقوی و مقدمه حسن مشکات طبسی،  در چاپخانه مجلس در تهران در سال ۱۳۱۹ش با عنوان « تازیانه سلوک»؛ به کوشش جواد نوربخش در سال ۱۳۵۲ش؛ به اهتمام احمد مجاهد ، ضمن مجموعه آثار فارسی احمد غزالی، از سوی انتشارات دانشگاه تهران در سال ۱۳۵۸ش و چاپ سوم در سال ۱۳۷۶ش",
        "منابع اثر، نمايه ها، چکيده ها": "کشف الظنون ۱: ۹۰۱؛ هدیه العارفین ۱: ۸۳؛ الذریعه ۲۳: ۳۲۹؛ ریحانه الادب ۴: ۲۳۴؛ روضات الجنات ۲: ۳۴۰؛  ایضاح المکنون  ۱: ۵۶۶؛ مشار فارسی ۱: ۳۵۱؛ دانشگاه  ۱۰: ۱۷۷۷؛ مرعشی  ۱۹: ۲۶ و ۱۳: ۹۰",
        "منبع تهیه": "خریداری از محمد رضا فرید تنکابنی درتاریخ ۲۳/۲/۸۵",
        "صحافي شده با :": "درر الدقائق و درر الحقائق / صدر الدین موفق بن محمد خاصی خوارزمی، احتمالا قرن ۱۰ق.1155052",
        "عنوانهای ديگر": "العینیه\nرساله عینیه\nتازیانه سلوک\nصلوات شریفه\nمکتوب الامام الغزالی الی عین القضاة الهمدانی",
        "موضوع": "عرفان -- متون قدیمی تا قرن ۱۴\nMysticism -- Early works to 20th century تصوف -- متون قدیمی تا قرن ۱۴\nSufism -- Early works to 20th century",
        "شناسه افزوده": "ف‍ری‍د ت‍ن‍ک‍اب‍ن‍ی، ع‍ب‍دال‍وه‍اب، ۱۲۸۶-، مالک قبلی فرید تنکابنی،محمدرضا،فروشنده"
    },
    "3158416": {
        "شناسه  سند": "۲۴۰/۱۰۲۳۳۲",
        "شناسه بازيابي": "۱۳/۱/۱۰۲۳۳۲",
        "عنوان": "اعتبارات لایروبی بنادر پهلوی و نوشهر از محل مطالبات دولت از شوروی [سند]",
        "سطح استاندارد": "پرونده",
        "منشا": "ایران. وزارت امور اقتصادی و دارایی",
        "تاریخ /دوره ایجاد": "۱۳۳۵.",
        "مشخصات ظاهری": "۱۰ برگ.",
        "دامنه و محتوا": "رسیدگی نخستوزیری به پیشنهاد وزارت راه و وزارت دارایی درخصوص تهیه وسایل لایروبی بنادر پهلوی و نوشهر از محل مطالبات دولت ایران از اتحاد جماهیر شوروی.",
        "توصیفگر": "ایران. وزارت دارایی\nایران. وزارت راه دی‍ون\nه‍زی‍ن‍ه ه‍ا\nمطالبات\nلاروبی نوشهر\nبندرانزلی\nروسیه شوروی",
        "مركز نگهداري سند": "آرشيو ملي ايران",
        "شناسه سند": "۲۴۰/۱۰۲۳۳۲",
        "دسترسی و محل الکترونیکی": " Ø¢Ø¯Ø±Ø³ Ø§ÙÚ©ØªØ±ÙÙÛÚ©Û ÙÙØ¨Ø¹ "
    },
    "3158417": {},
    "3158418": {
        "شناسه  سند": "۲۴۰/۱۰۲۳۳۱",
        "شناسه بازيابي": "۱۳/۱/۱۰۲۳۳۱",
        "عنوان": "رسیدگی به اتهام اخذ رشوه  توسط محمود مصاحب در سیلوی تهران [سند]",
        "سطح استاندارد": "پرونده",
        "منشا": "ایران. وزارت امور اقتصادی و دارایی",
        "تاریخ /دوره ایجاد": "۱۳۲۲ـ۱۳۳۷.",
        "مشخصات ظاهری": "۷۰ برگ.",
        "دامنه و محتوا": "رسیدگی اداره کل بازرسی وزارت دارایی و اداره بازرسی غله و نان به اتهام اخذ رشوه توسط محمود مصاحب رئیس بازرسی سیلوی تهران.",
        "توصیفگر": "ایران. وزارت دارایی. اداره دارایی تهران سیلوها\nب‍ازرس‍ی\nارت‍ش‍اء\nخطای شغلی \nتخلفات اداری\nک‍ارک‍ن‍ان دول‍ت تهران",
        "مركز نگهداري سند": "آرشيو ملي ايران",
        "شناسه سند": "۲۴۰/۱۰۲۳۳۱"
    },
    "3158419": {
        "شناسه  سند": "۲۴۰/۱۰۲۳۳۰",
        "شناسه بازيابي": "۱۳/۱/۱۰۲۳۳۰",
        "عنوان": "مالیات بر درآمد اصناف، مزارع، املاک و حقوق دیوانی [سند]",
        "سطح استاندارد": "پرونده",
        "منشا": "ایران. وزارت امور اقتصادی و دارایی",
        "تاریخ /دوره ایجاد": "۱۳۳۰ـ۱۳۳۲ق.",
        "مشخصات ظاهری": "۱۵۰ برگ.",
        "يادداشت": "تعدادی از برگهای پرونده به زبان فرانسه است.",
        "دامنه و محتوا": "رسیدگی وزارت مالیه به شکایت صنف صباغ و نداف یزد درخصوص مالیات صنفی آنها، وصول مالیات مزرعه رشکوئیه یزد و باغات سیدجواد یزدی و نیز مالیات املاک قوامالسادات و مالیات و حقوق دیوانی نواب وکیلالتولیه و سلسله نوابی، رسیدگی به شکایت سادات میبد درخصوص مالیات.",
        "توصیفگر": "ایران. وزارت مالیه م‍ال‍ی‍اته‍ا\nم‍ال‍ک‍ان\nاص‍ن‍اف\nس‍ادات\nروستاها\nملک\nش‍ک‍ای‍ت\nب‍اغه‍ا\nام‍ن‍ی‍ت\nح‍ق‍وق و دس‍ت‍م‍زده‍ا\nم‍ال‍ی‍ات ب‍ر درآم‍د یزد\nمیبد",
        "مركز نگهداري سند": "آرشيو ملي ايران",
        "شناسه سند": "۲۴۰/۱۰۲۳۳۰"
    },
    "3158420": {},
    "3158421": {
        "شناسه  سند": "۲۴۰/۱۰۲۳۲۹",
        "شناسه بازيابي": "۱۳/۱/۱۰۲۳۲۹",
        "عنوان": "رفع توقیف از املاک سیدابراهیم نظری [سند]",
        "سطح استاندارد": "پرونده",
        "منشا": "ایران. وزارت امور اقتصادی و دارایی",
        "تاریخ /دوره ایجاد": "۱۲۹۹ـ۱۳۰۰.",
        "مشخصات ظاهری": "۱۵ برگ.",
        "دامنه و محتوا": "رسیدگی اداره تشخیص عایدات وزارت مالیه به درخواست سیدابراهیم نظری درخصوص رفع توقیف از املاک وی در نطنز.",
        "توصیفگر": "ایران. وزارت مالیه ام‍ن‍ی‍ت\nت‍وق‍ی‍ف ام‍وال\nمستغلات\nش‍ک‍ای‍ت\nم‍ال‍ک‍ان\nم‍ص‍ادره ام‍وال\nراهزنان نطنز\nکاشان",
        "مركز نگهداري سند": "آرشيو ملي ايران",
        "شناسه سند": "۲۴۰/۱۰۲۳۲۹"
    },
    "3158422": {},
    "3158423": {},
    "3158424": {},
    "3158425": {
        "شناسه  سند": "۲۴۰/۱۰۲۳۲۸",
        "شناسه بازيابي": "۱۳/۱/۱۰۲۳۲۸",
        "عنوان": "رفع توقیف از املاک میرزا حسن نجار [سند]",
        "سطح استاندارد": "پرونده",
        "منشا": "ایران. وزارت امور اقتصادی و دارایی",
        "تاریخ /دوره ایجاد": "۱۲۹۹.",
        "مشخصات ظاهری": "۲۰ برگ.",
        "دامنه و محتوا": "رسیدگی اداره تشخیص عایدات وزارت مالیه به تقاضای میرزا حسن نجار بزرگی درخصوص رفع توقیف از املاک وی در کاشان.",
        "توصیفگر": "ایران. وزارت مالیه م‍ال‍ک‍ان\nمستغلات\nام‍ن‍ی‍ت\nت‍وق‍ی‍ف ام‍وال\nم‍ص‍ادره ام‍وال\nش‍ک‍ای‍ت\nراهزنان کاشان",
        "مركز نگهداري سند": "آرشيو ملي ايران",
        "شناسه سند": "۲۴۰/۱۰۲۳۲۸"
    },
    "3158426": {},
    "3158427": {},
    "3158428": {
        "شناسه  سند": "۲۴۰/۱۰۲۳۲۷",
        "شناسه بازيابي": "۱۳/۱/۱۰۲۳۲۷",
        "عنوان": "رفع تعویض از املاک محققالدوله [سند]",
        "سطح استاندارد": "پرونده",
        "منشا": "ایران. وزارت امور اقتصادی و دارایی",
        "تاریخ /دوره ایجاد": "۱۲۹۹.",
        "مشخصات ظاهری": "۴۰ برگ.",
        "دامنه و محتوا": "رسیدگی اداره تشخیص عایدات وزارت مالیه به درخواست محققالدوله درخصوص معاوضه کاروانسرای وی در کاشان با یکی از املاک خالصه دولتی.",
        "توصیفگر": "ایران. وزارت مالیه مستغلات\nم‍ال‍ک‍ان\nاراض‍ی ع‍م‍وم‍ی\nن‍ی‍روه‍ای م‍س‍ل‍ح کاشان",
        "مركز نگهداري سند": "آرشيو ملي ايران",
        "شناسه سند": "۲۴۰/۱۰۲۳۲۷",
        "دسترسی و محل الکترونیکی": " Ø¢Ø¯Ø±Ø³ Ø§ÙÚ©ØªØ±ÙÙÛÚ©Û ÙÙØ¨Ø¹ "
    },
    "3158429": {
        "شماره کتابشناسی ملی": "۳۱۵۸۴۲۹",
        "عنوان و  نام پديدآور": "[اعتراض سازمان ملی دانشگاهیان (دانشگاه تهران) از تعطیلی دانشگاه] [اعلامیه]/سازمان ملی دانشگاهیان (دانشگاه تهران)",
        "وضعیت نشر": "[بی جا: بی نا،  ۱۳۵۷].",
        "مشخصات ظاهری": "[۱] ورق.",
        "وضعیت فهرست نویسی": "اطلاعات ثبت"
    },
    "3158430": {
        "شناسه  سند": "۲۴۰/۱۰۲۳۲۶",
        "شناسه بازيابي": "۱۳/۱/۱۰۲۳۲۶",
        "عنوان": "خرید شکر [سند]",
        "سطح استاندارد": "پرونده",
        "منشا": "ایران. وزارت امور اقتصادی و دارایی",
        "تاریخ /دوره ایجاد": "۱۳۳۱ـ۱۳۳۲.۱۳۳۴.",
        "مشخصات ظاهری": "۲ برگ.",
        "دامنه و محتوا": "گزارش نمایندگی دائمی ایران در سازمان ملل متحد راجع به قرارداد بینالمللی قند ارسال شده توسط وزارت امور خارجه به وزارت دارایی، خرید شکر مورد نیاز توسط وزارت دارایی به همراه آمار موجودی قند و شکر شهرستانها.",
        "توصیفگر": "ایران. وزارت امور خارجه\nسازمان ملل متحد\nایران. وزارت دارایی ق‍رارداد ه‍ا\nقند و شکر\nگ‍زارش ه‍ا\nخ‍ری‍د\nواردات",
        "مركز نگهداري سند": "آرشيو ملي ايران",
        "شناسه سند": "۲۴۰/۱۰۲۳۲۶"
    },
    "3158431": {},
    "3158432": {
        "شماره کتابشناسی ملی": "۳۱۵۸۴۳۲",
        "عنوان و  نام پديدآور": "[اعلامیه اعضاء هیات علمی دانشگاه ابوریحان بیرونی (پردیزه مامازند) برای مبارزه با امپریالیسم آمریکا] [اعلامیه]/اعضاء هیات علمی دانشگاه ابوریحان بیرونی",
        "وضعیت نشر": "[بی جا: بی نا،  ۱۳۵۷].",
        "مشخصات ظاهری": "[۱] ورق.",
        "وضعیت فهرست نویسی": "اطلاعات ثبت"
    },
    "3158433": {
        "شناسه  سند": "۲۴۰/۱۰۲۳۲۳",
        "شناسه بازيابي": "۱۳/۱/۱۰۲۳۲۳",
        "عنوان": "مالیات بر ارث ابوالحسن پیرنیا در نائین [سند]",
        "سطح استاندارد": "پرونده",
        "منشا": "ایران. وزارت امور اقتصادی و دارایی",
        "تاریخ /دوره ایجاد": "۱۳۱۸ـ۱۳۲۰.",
        "مشخصات ظاهری": "۷۰ برگ.",
        "دامنه و محتوا": "رسیدگی اداره مالیات بر درآمد تهران درخصوص تعیین ارزش املاک ابوالحسن پیرنیا در نائین و اخذ مالیات از وراث وی.",
        "توصیفگر": "پیرنیا، ابوالحسن، ۱۲۴۸ - ۱۳۱۸. ایران. وزارت دارایی مستغلات\nقناتها\nم‍ال‍ی‍اته‍ا\nم‍ال‍ی‍ات ب‍ر ارث\nم‍ال‍ک‍ان نایین\nتهران",
        "مركز نگهداري سند": "آرشيو ملي ايران",
        "شناسه سند": "۲۴۰/۱۰۲۳۲۳",
        "دسترسی و محل الکترونیکی": " Ø¢Ø¯Ø±Ø³ Ø§ÙÚ©ØªØ±ÙÙÛÚ©Û ÙÙØ¨Ø¹ "
    },
    "3158434": {},
    "3158435": {
        "شماره کتابشناسی ملی": "۳۱۵۸۴۳۵",
        "عنوان و  نام پديدآور": "[خواستهای جنبش دانشجویی] [اعلامیه]",
        "وضعیت نشر": "[بی جا: بی نا،  ××۱۳].",
        "مشخصات ظاهری": "[۲] ورق.",
        "وضعیت فهرست نویسی": "اطلاعات ثبت"
    },
    "3158436": {},
    "3158437": {
        "شناسه  سند": "۲۴۰/۱۰۲۳۲۲",
        "شناسه بازيابي": "۱۳/۱/۱۰۲۳۲۲",
        "عنوان": "توزیع بذر پنبه و مبارزه با آفت آن در فارس و کرمان [سند]",
        "سطح استاندارد": "پرونده",
        "منشا": "ایران. وزارت امور اقتصادی و دارایی",
        "تاریخ /دوره ایجاد": "۱۳۱۷.",
        "مشخصات ظاهری": "۸۰ برگ.",
        "دامنه و محتوا": "توزیع بذر پنبه در حوزه فارس توسط شعبات شرکت سهامی پنبه و پشم و پوست و مبارزه با آفت کرم سرخ پنبه در کرمان و داراب.",
        "توصیفگر": "شرکت سهامی پنبه و پشم و پوست پنبه\nت‍ول‍ی‍دات ک‍ش‍اورزی داراب \nفارس\nکرمان",
        "مركز نگهداري سند": "آرشيو ملي ايران",
        "شناسه سند": "۲۴۰/۱۰۲۳۲۲"
    },
    "3158438": {},
    "3158439": {
        "شماره کتابشناسی ملی": "۳۱۵۸۴۳۹",
        "عنوان و  نام پديدآور": "اطلاعیه [دعوت برای شرکت در شورای دانشجوئی دانشگاه] [اعلامیه]/شورای دانشجوئی دانشگاه",
        "وضعیت نشر": "[بی جا: بی نا،  ۱۳۵۹].",
        "مشخصات ظاهری": "[۱] ورق.",
        "وضعیت فهرست نویسی": "اطلاعات ثبت"
    },
    "3158440": {
        "شماره کتابشناسی ملی": "۳۱۵۸۴۴۰",
        "عنوان و  نام پديدآور": "[درخواست از آقای منهدس بازرگان در مورد ایجاد فضای مناسب برای فعالیت مجاهدین] [اعلامیه]/انجمن دانشجویان مسلمان دانشگاه تهران",
        "وضعیت نشر": "[بی جا: بی نا،  ۱۳۵۸].",
        "مشخصات ظاهری": "[۱] ورق.",
        "وضعیت فهرست نویسی": "اطلاعات ثبت"
    },
    "3158441": {
        "شناسه  سند": "۲۴۰/۱۰۲۳۲۱",
        "شناسه بازيابي": "۱۳/۱/۱۰۲۳۲۱",
        "عنوان": "توقیف اموال اشرار کاشان [سند]",
        "سطح استاندارد": "پرونده",
        "منشا": "ایران. وزارت امور اقتصادی و دارایی",
        "تاریخ /دوره ایجاد": "۱۲۹۹.",
        "مشخصات ظاهری": "۳۰ برگ.",
        "دامنه و محتوا": "رسیدگی اداره تشخیص عایدات وزارت مالیه به شکایت ماشاءاله سوختهفروش درخصوص توقیف املاک وی در کاشان به همراه املاک اشرار آنجا.",
        "توصیفگر": "ایران. وزارت مالیه م‍ال‍ک‍ان\nمستغلات\nت‍وق‍ی‍ف ام‍وال\nب‍اغه‍ا کاشان",
        "مركز نگهداري سند": "آرشيو ملي ايران",
        "شناسه سند": "۲۴۰/۱۰۲۳۲۱"
    },
    "3158442": {},
    "3158443": {
        "شماره کتابشناسی ملی": "۳۱۵۸۴۴۳",
        "عنوان و  نام پديدآور": "[پشتیبانی از رهنمودهای امام خمینی] [اعلامیه]/انجمن اسلامی مجتمع علوم پیراپزشکی",
        "وضعیت نشر": "[بی جا: بی نا،  ۱۳۵۹].",
        "مشخصات ظاهری": "[۲]ص.",
        "وضعیت فهرست نویسی": "اطلاعات ثبت"
    },
    "3158444": {},
    "3158445": {
        "شماره کتابشناسی ملی": "۳۱۵۸۴۴۵",
        "عنوان و  نام پديدآور": "[تشکیل حزب جمهوری اسلامی خلق مسلمان ایران] [اعلامیه]",
        "وضعیت نشر": "[بی جا: بی نا،  ۱۳۵۷].",
        "مشخصات ظاهری": "[۱] ورق.",
        "وضعیت فهرست نویسی": "اطلاعات ثبت"
    },
    "3158446": {
        "شناسه  سند": "۲۴۰/۱۰۲۳۲۰",
        "شناسه بازيابي": "۱۳/۱/۱۰۲۳۲۰",
        "عنوان": "وصول مالیات املاک حاج باقر دهالی در نیاسر کاشان [سند]",
        "سطح استاندارد": "پرونده",
        "منشا": "ایران. وزارت امور اقتصادی و دارایی",
        "تاریخ /دوره ایجاد": "۱۳۰۷ـ۱۳۰۸.",
        "مشخصات ظاهری": "۳۰ برگ.",
        "دامنه و محتوا": "رسیدگی اداره کل عایدات وزارت مالیه به شکایت حاج باقر دهالی درخصوص مالیات املاک وی در نیاسر کاشان.",
        "توصیفگر": "ایران. وزارت مالیه م‍ال‍ی‍اته‍ا\nم‍ال‍ک‍ان\nش‍ک‍ای‍ت کاشان\nنیاسر",
        "مركز نگهداري سند": "آرشيو ملي ايران",
        "شناسه سند": "۲۴۰/۱۰۲۳۲۰"
    },
    "3158447": {
        "شماره کتابشناسی ملی": "۳۱۵۸۴۴۷",
        "عنوان و  نام پديدآور": "[بررسی مسائل انتخابات] [اعلامیه]/حزب جمهوری اسلامی",
        "وضعیت نشر": "[بی جا: بی نا،  ۱۳۵۸].",
        "مشخصات ظاهری": "[۱] ورق.",
        "وضعیت فهرست نویسی": "اطلاعات ثبت"
    },
    "3158448": {},
    "3158449": {},
    "3158450": {
        "شماره کتابشناسی ملی": "۳۱۵۸۴۵۰",
        "عنوان و  نام پديدآور": "[اعلامیه راجع به حذف دو مرحله ای کردن انتخابات] [اعلامیه]/انجمن هنرجویان مسلمان هنرستان پیشه",
        "وضعیت نشر": "[بی جا: بی نا،  ××۱۳].",
        "مشخصات ظاهری": "[۱] ورق.",
        "وضعیت فهرست نویسی": "اطلاعات ثبت"
    },
    "3158451": {
        "شناسه  سند": "۲۴۰/۱۰۲۳۱۹",
        "شناسه بازيابي": "۱۳/۱/۱۰۲۳۱۹",
        "عنوان": "شکایت از تعدیات حاکم بختیاری یزد در وصول مالیات [سند]",
        "سطح استاندارد": "پرونده",
        "منشا": "ایران. وزارت امور اقتصادی و دارایی",
        "تاریخ /دوره ایجاد": "۱۳۳۱ق.",
        "مشخصات ظاهری": "۲۵ برگ.",
        "يادداشت": "تعدادی از برگهای پرونده به زبان فرانسه است.",
        "دامنه و محتوا": "رسیدگی خزانهداریكل به شكايت شارقالملک از تعدیات حاکم بختیاری یزد در وصول مالیات.",
        "توصیفگر": "ایران. وزارت مالیه. خزانهداری کل م‍ال‍ی‍اته‍ا\nش‍ک‍ای‍ت\nاستانداران و فرمانداران \nGovernors\nت‍ع‍دی در وظای‍ف دول‍ت‍ی یزد",
        "مركز نگهداري سند": "آرشيو ملي ايران",
        "شناسه سند": "۲۴۰/۱۰۲۳۱۹",
        "دسترسی و محل الکترونیکی": " Ø¢Ø¯Ø±Ø³ Ø§ÙÚ©ØªØ±ÙÙÛÚ©Û ÙÙØ¨Ø¹ "
    },
    "3158452": {
        "شماره کتابشناسی ملی": "۳۱۵۸۴۵۲",
        "عنوان و  نام پديدآور": "[بزرگداشت ۱۱ اردیبهشت- اول ماه مه] [اعلامیه]/انجمن اسلامی دانش آموزان دبیرستان جاویدان",
        "وضعیت نشر": "[بی جا: بی نا،  ××۱۳].",
        "مشخصات ظاهری": "[۱] ورق.",
        "وضعیت فهرست نویسی": "اطلاعات ثبت"
    },
    "3158453": {
        "شناسه  سند": "۲۴۰/۷۷۰۶۹",
        "شناسه بازيابي": "۱۳/۱/۷۷۰۶۹",
        "عنوان": "صورت مسافت و فواصل خطوط مواصلاتی شهرهای مختلف کشور بر حسب میل[سند]",
        "سطح استاندارد": "پرونده",
        "منشا": "ایران. وزارت امور اقتصادی و دارایی",
        "تاریخ /دوره ایجاد": "۱۳۰۸.",
        "مشخصات ظاهری": "۸ برگ.",
        "دامنه و محتوا": "صورت مسافت و فواصل خطوط مواصلاتی شهرهای مختلف کشور بر حسب میل و تذکر چند اشتباه رخ داده در این خصوص.",
        "توصیفگر": "ایران. وزارت مالیه راهه‍ا\nشهرها و شهرستانها\nآم‍ار",
        "مركز نگهداري سند": "آرشيو ملي ايران",
        "شناسه سند": "۲۴۰/۷۷۰۶۹"
    },
    "3158454": {},
    "3158455": {
        "شماره کتابشناسی ملی": "۳۱۵۸۴۵۵",
        "عنوان و  نام پديدآور": "[تحریم کالاهای آمریکائی] [اعلامیه]/انجمن قرآن دبیرستان زهرا ملک پور",
        "وضعیت نشر": "[بی جا: بی نا،  ××۱۳].",
        "مشخصات ظاهری": "[۱] ورق.",
        "وضعیت فهرست نویسی": "اطلاعات ثبت"
    },
    "3158456": {
        "شناسه  سند": "۲۴۰/۷۷۰۷۰",
        "شناسه بازيابي": "۱۳/۱/۷۷۰۷۰",
        "عنوان": "صورت مجلس کمیسیون مسول بررسی قضایای قاچاق کالا و صورت مجلس های گمرک بوشهر با حضور اطراف طرف دعوی[سند]",
        "سطح استاندارد": "پرونده",
        "منشا": "ایران. وزارت امور اقتصادی و دارایی",
        "تاریخ /دوره ایجاد": "۱۳۰۷.",
        "مشخصات ظاهری": "۳۵ برگ.",
        "دامنه و محتوا": "صورت مجلس کمیسیون مسئول بررسی قضایای قاچاق کالا و صورت مجلس های گمرک بوشهر با حضور طرفین و صدور جرایم و احکام ویژه.",
        "توصیفگر": "ایران. وزارت مالیه گ‍م‍رک\nقند و شکر\nه‍زی‍ن‍ه ه‍ا\nج‍رای‍م اق‍ت‍ص‍ادی\nق‍اچ‍اق بوشهر",
        "مركز نگهداري سند": "آرشيو ملي ايران",
        "شناسه سند": "۲۴۰/۷۷۰۷۰"
    },
    "3158457": {
        "شناسه  سند": "۲۴۰/۱۰۲۳۱۸",
        "شناسه بازيابي": "۱۳/۱/۱۰۲۳۱۸",
        "عنوان": "شکایت از توقیف اموال سیدعبدالرحیم کاشانی [سند]",
        "سطح استاندارد": "پرونده",
        "منشا": "ایران. وزارت امور اقتصادی و دارایی",
        "تاریخ /دوره ایجاد": "۱۲۹۹.",
        "مشخصات ظاهری": "۳ برگ.",
        "دامنه و محتوا": "شکایت سیدعبدالرحیم کاشانی درخصوص توقیف اموال و املاک وی توسط اداره مالیه کاشان.",
        "توصیفگر": "ایران. وزارت مالیه م‍ال‍ک‍ان\nش‍ک‍ای‍ت\nت‍وق‍ی‍ف ام‍وال\nام‍وال  غ‍ی‍رم‍ن‍ق‍ول\nملک کاشان",
        "مركز نگهداري سند": "آرشيو ملي ايران",
        "شناسه سند": "۲۴۰/۱۰۲۳۱۸"
    },
    "3158458": {
        "شناسه  سند": "۲۴۰/۷۷۰۷۱",
        "شناسه بازيابي": "۱۳/۱/۷۷۰۷۱",
        "عنوان": "صورت موجودی اموال منقول دولتی بنگاه انحصار تریاک دارایی مسجد سلیمان[سند]",
        "سطح استاندارد": "پرونده",
        "منشا": "ایران. وزارت امور اقتصادی و دارایی",
        "تاریخ /دوره ایجاد": "۱۳۲۶-۱۳۳۰.",
        "مشخصات ظاهری": "۷ برگ.",
        "دامنه و محتوا": "صورت موجودی اموال منقول دولتی بنگاه انحصار تریاک دارایی مسجد سلیمان.",
        "توصیفگر": "ایران. وزارت دارایی آم‍ار\nتریاک\nش‍ه‍رداریه‍ا\nام‍وال م‍ن‍ق‍ول مسجد سلیمان",
        "مركز نگهداري سند": "آرشيو ملي ايران",
        "شناسه سند": "۲۴۰/۷۷۰۷۱"
    },
    "3158459": {
        "شماره کتابشناسی ملی": "۳۱۵۸۴۵۹",
        "عنوان و  نام پديدآور": "بیانیه شماره ۵ [اتحادیه انجمن های اسلامی دانش آموزان] [اعلامیه]/اتحادیه انجمن های اسلامی دانش آموزان",
        "وضعیت نشر": "[بی جا: بی نا،  ××۱۳].",
        "مشخصات ظاهری": "[۲]ص.",
        "وضعیت فهرست نویسی": "اطلاعات ثبت"
    },
    "3158460": {
        "شماره کتابشناسی ملی": "۳۱۵۸۴۶۰",
        "عنوان و  نام پديدآور": "بیانیه شماره ۶ [اتحادیه انجمن های اسلامی دانش آموزان] [اعلامیه]/اتحادیه انجمن های اسلامی دانش آموزان",
        "وضعیت نشر": "[بی جا: بی نا،  ۱۳۵۸].",
        "مشخصات ظاهری": "[۱] ورق.",
        "وضعیت فهرست نویسی": "اطلاعات ثبت"
    },
    "3158461": {
        "شناسه  سند": "۲۴۰/۷۷۰۷۲",
        "شناسه بازيابي": "۱۳/۱/۷۷۰۷۲",
        "عنوان": "گزارش بازرس وزارتی از وضعیت مالی راه آهن جنوب به همراه آمار و ارقام[سند]",
        "سطح استاندارد": "پرونده",
        "منشا": "ایران. وزارت امور اقتصادی و دارایی",
        "تاریخ /دوره ایجاد": "۱۳۰۹-۱۳۱۰.",
        "مشخصات ظاهری": "۸ برگ.",
        "دامنه و محتوا": "گزارش بازرس وزارتی از وضعیت مالی راه آهن جنوب به همراه آمار و ارقام و صورت وضعیت عایدات ٬ پرداخت و ذکر نواقص موجود در این اداره قبل از ورود مترکارل.",
        "توصیفگر": "ب‍ازرس‍ی\nآم‍ار\nم‍دی‍ری‍ت م‍ال‍ی\nاض‍اف‍ه ک‍ار\nح‍ق‍وق و دس‍ت‍م‍زده‍ا\nک‍ارک‍ن‍ان دول‍ت\nوض‍ع‍ی‍ت م‍ال‍ی\nراهآه‍ن\nگ‍زارش ه‍ا",
        "مركز نگهداري سند": "آرشيو ملي ايران",
        "شناسه سند": "۲۴۰/۷۷۰۷۲"
    },
    "3158462": {
        "شناسه  سند": "۲۴۰/۱۰۲۳۱۷",
        "شناسه بازيابي": "۱۳/۱/۱۰۲۳۱۷",
        "عنوان": "شکایت امور مالیاتی اهالی قریه دهنو یزد [سند]",
        "سطح استاندارد": "پرونده",
        "منشا": "ایران. وزارت امور اقتصادی و دارایی",
        "تاریخ /دوره ایجاد": "۱۳۳۱ـ۱۳۳۲ق.",
        "مشخصات ظاهری": "۲۰ برگ.",
        "يادداشت": "تعدادی از برگهای پرونده به زبان فرانسه است.",
        "دامنه و محتوا": "رسیدگی خزانهداری کل و اداره مالیه یزد به شکایت اهالی قریه دهنو از تعدیات حکومت یزد در اخذ مالیات اضافی از آنها.",
        "توصیفگر": "ایران. وزارت مالیه روستاها\nاستانداران و فرمانداران \nم‍ال‍ی‍اته‍ا\nش‍ک‍ای‍ت یزد",
        "مركز نگهداري سند": "آرشيو ملي ايران",
        "شناسه سند": "۲۴۰/۱۰۲۳۱۷"
    },
    "3158463": {
        "شماره کتابشناسی ملی": "۳۱۵۸۴۶۳",
        "عنوان و  نام پديدآور": "[کمک به مردم مسلمان افغانستان] [اعلامیه]/انجمن اسلامی دبیرستان خامنه ای",
        "وضعیت نشر": "[بی جا: بی نا،  ۱۳۵۸].",
        "مشخصات ظاهری": "[۱] ورق.",
        "وضعیت فهرست نویسی": "اطلاعات ثبت"
    },
    "3158464": {
        "شناسه  سند": "۲۴۰/۷۷۰۷۳",
        "شناسه بازيابي": "۱۳/۱/۷۷۰۷۳",
        "عنوان": "بخشنامه وزارتی مبنی بر لزوم ذکر رضایت وزارتخانه ها از کارمندان طالب دخول در وزارتخانه های دیگر[سند]",
        "سطح استاندارد": "برگ",
        "منشا": "ایران. وزارت امور اقتصادی و دارایی",
        "تاریخ /دوره ایجاد": "۱۳۲۰.",
        "مشخصات ظاهری": "۱ برگ.",
        "دامنه و محتوا": "بخشنامه وزارتی مبنی بر لزوم ذکر رضایت وزارتخانه ها از کارمندان طالب دخول در وزارتخانه های دیگر در احکام معافیت آنها جهت تسریع در امر پرداخت حقوق و اشتغال آنها.",
        "توصیفگر": "وزارت خ‍ان‍ه ه‍ا\nح‍ق‍وق و دس‍ت‍م‍زده‍ا\nاش‍ت‍غ‍ال\nک‍ارک‍ن‍ان دول‍ت\nان‍ت‍ق‍ال\nبخشنامهها",
        "مركز نگهداري سند": "آرشيو ملي ايران",
        "شناسه سند": "۲۴۰/۷۷۰۷۳"
    },
    "3158465": {
        "شماره کتابشناسی ملی": "۳۱۵۸۴۶۵",
        "عنوان و  نام پديدآور": "[پشتیبانی از خواسته های برحق برادران مسلمان] [اعلامیه]/انجمن اسلامی دبیرستان دانشگاه ملی ایران",
        "وضعیت نشر": "[بی جا: بی نا،  ۱۳۵۸].",
        "مشخصات ظاهری": "[۲]ص.",
        "وضعیت فهرست نویسی": "اطلاعات ثبت"
    },
    "3158466": {
        "شناسه  سند": "۲۴۰/۷۷۰۷۴",
        "شناسه بازيابي": "۱۳/۱/۷۷۰۷۴",
        "عنوان": "صورت مجالس اداره گمرکات کرمانشاه مبنی بر صدور مجوز حمل کالا به سرحدات[سند]",
        "سطح استاندارد": "پرونده",
        "منشا": "ایران. وزارت امور اقتصادی و دارایی",
        "تاریخ /دوره ایجاد": "۱۳۱۰.",
        "مشخصات ظاهری": "۶۶ برگ.",
        "دامنه و محتوا": "صورت مجالس اداره گمرکات کرمانشاه مبنی بر صدور جواز خروج کالاهای تجار به سرحدات.",
        "توصیفگر": "اجازهنامهها و پروانهها\nم‍رزه‍ا\nکالاها\nپوست\nب‍ازرگ‍ان‍ان\nپارچه کرمانشاه",
        "مركز نگهداري سند": "آرشيو ملي ايران",
        "شناسه سند": "۲۴۰/۷۷۰۷۴"
    },
    "3158467": {
        "شناسه  سند": "۲۴۰/۱۰۲۳۱۶",
        "شناسه بازيابي": "۱۳/۱/۱۰۲۳۱۶",
        "عنوان": "مالیات قریه کله کاشان [سند]",
        "سطح استاندارد": "پرونده",
        "منشا": "ایران. وزارت امور اقتصادی و دارایی",
        "تاریخ /دوره ایجاد": "۱۳۰۸.",
        "مشخصات ظاهری": "۱۵ برگ.",
        "دامنه و محتوا": "درخواست اداره مالیه کاشان از اداره تشخیص عایدات وزارت مالیه درخصوص رسیدگی به شکایت اهالی قریه کله راجع به لزوم تخفیف در مالیات آنها به دلیل کمآبی و سرمازدگی محصول سردرختی قریه مزبور.",
        "توصیفگر": "ایران. وزارت مالیه. اداره مالیه کاشان روستاها\nم‍ال‍ی‍اته‍ا\nش‍ک‍ای‍ت کاشان",
        "مركز نگهداري سند": "آرشيو ملي ايران",
        "شناسه سند": "۲۴۰/۱۰۲۳۱۶"
    },
    "3158468": {
        "شناسه  سند": "۲۴۰/۷۷۰۷۵",
        "شناسه بازيابي": "۱۳/۱/۷۷۰۷۵",
        "عنوان": "درخواست شرکت موتورازاکئو از اداره گمرکات جهت صدور جواز ورود و ترخیص کالاها و ماشین آلات[سند]",
        "سطح استاندارد": "پرونده",
        "منشا": "ایران. وزارت امور اقتصادی و دارایی",
        "تاریخ /دوره ایجاد": "۱۳۱۳.",
        "مشخصات ظاهری": "۵ برگ.",
        "دامنه و محتوا": "درخواست شرکت موتورازاکئو از اداره گمرکات جهت صدور جواز ورود و ترخیص کالاها و ماشین آلات مورد نیاز جهت ساخت راه آهن.",
        "توصیفگر": "اجازهنامهها و پروانهها\nش‍رک‍ته‍ای خ‍ارج‍ی\nراهآه‍ن\nترخیص\nماشینآلات\nگ‍م‍رک",
        "مركز نگهداري سند": "آرشيو ملي ايران",
        "شناسه سند": "۲۴۰/۷۷۰۷۵"
    },
    "3158469": {
        "شناسه  سند": "۲۴۰/۷۷۰۷۶",
        "شناسه بازيابي": "۱۳/۱/۷۷۰۷۶",
        "عنوان": "محاسبه و اخذ تمبر بارهای حمل شده از طریق بنگاه راه آهن دولتی [سند]",
        "سطح استاندارد": "پرونده",
        "منشا": "ایران. وزارت امور اقتصادی و دارایی",
        "تاریخ /دوره ایجاد": "۱۳۱۹.",
        "مشخصات ظاهری": "۲۴ برگ.",
        "دامنه و محتوا": "محاسبه و اخذ تمبر بارهای حمل شده از آذربایجان غربی از طریق بنگاه راه آهن دولتی و لزوم صدور بارنامه جداگانه برای کالاهای موجود در اتومبیل ها و واگنها.",
        "توصیفگر": "ایران. وزارت راه اوزان و مقیاسها\nح‍م‍ل و ن‍ق‍ل زم‍ی‍ن‍ی\nکالاها\nتمبر\nق‍ی‍م‍ت ه‍ا\nراهآه‍ن آذربایجان غربی ",
        "مركز نگهداري سند": "آرشيو ملي ايران",
        "شناسه سند": "۲۴۰/۷۷۰۷۶"
    },
    "3158470": {
        "شناسه  سند": "۲۴۰/۱۰۲۳۱۵",
        "شناسه بازيابي": "۱۳/۱/۱۰۲۳۱۵",
        "عنوان": "وصول مالیات معدن مس انارک [سند]",
        "سطح استاندارد": "پرونده",
        "منشا": "ایران. وزارت امور اقتصادی و دارایی",
        "تاریخ /دوره ایجاد": "۱۳۳۱ـ۱۳۳۲ق.",
        "مشخصات ظاهری": "۳۰ برگ.",
        "يادداشت": "تعدادی از برگهای پرونده به زبان فرانسه است.",
        "دامنه و محتوا": "رسیدگی وزارت مالیه و خزانهداری کل درخصوص وصول مالیات معدن مس انارک و نیز وصول مالیات بلوک بهاباد و برات و شهر بابک و نائین توسط نایبالحكومههای بلوک مزبور با نظارت حاكم يزد.",
        "توصیفگر": "ایران. وزارت مالیه م‍ع‍ادن\nاستانداران و فرمانداران \nم‍ال‍ی‍اته‍ا یزد\nنایین\nشهر بابک\nانارک ",
        "مركز نگهداري سند": "آرشيو ملي ايران",
        "شناسه سند": "۲۴۰/۱۰۲۳۱۵",
        "دسترسی و محل الکترونیکی": " Ø¢Ø¯Ø±Ø³ Ø§ÙÚ©ØªØ±ÙÙÛÚ©Û ÙÙØ¨Ø¹ "
    },
    "3158471": {
        "شناسه  سند": "۲۴۰/۷۷۰۷۷",
        "شناسه بازيابي": "۱۳/۱/۷۷۰۷۷",
        "عنوان": "رسیدگی به شکایت مستاجر قریه صادق آباد در خصوص اجاره آن[سند]",
        "سطح استاندارد": "پرونده",
        "منشا": "ایران. وزارت امور اقتصادی و دارایی",
        "تاریخ /دوره ایجاد": "۱۳۳۳.",
        "مشخصات ظاهری": "۸ برگ.",
        "دامنه و محتوا": "شکایت اسدالله فیض آبادی در باب اجاره سه دانگ و نیم قریه صادق آباد و اخذ مال الاجاره با جبر از سوی مالیه و مطالبه مجدد مال الاجاره از سوی مالک ملک مزبور.",
        "توصیفگر": "ملک\nروس‍ت‍ا [۱]\nاراض‍ی ک‍ش‍اورزی\nم‍ال‍ک‍ان\nاجارهبها\nش‍ک‍ای‍ت",
        "مركز نگهداري سند": "آرشيو ملي ايران",
        "شناسه سند": "۲۴۰/۷۷۰۷۷"
    },
    "3158472": {
        "شناسه  سند": "۲۴۰/۷۷۰۷۸",
        "شناسه بازيابي": "۱۳/۱/۷۷۰۷۸",
        "عنوان": "درخواست فروش دویست تن دانه مرغی مورد مزایده با قیمت عادلانه به اداره دفع آفات نباتی شیراز[سند]",
        "سطح استاندارد": "پرونده",
        "منشا": "ایران. وزارت امور اقتصادی و دارایی",
        "تاریخ /دوره ایجاد": "۱۳۲۰.",
        "مشخصات ظاهری": "۸ برگ.",
        "دامنه و محتوا": "درخواست دارایی از وزارت کشاورزی جهت فروش دویست تن دانه مرغی مورد مزایده با قیمت عادلانه به اداره دفع آفات نباتی شیراز جهت تهیه ماده مسموم دفع ملخ دریایی.",
        "توصیفگر": "ایران. وزارت کشاورزی ف‍روش\nمرغداری\nسبوس\nدانهها\nآفت\nم‍زای‍ده ه‍ا شیراز\nفسا",
        "مركز نگهداري سند": "آرشيو ملي ايران",
        "شناسه سند": "۲۴۰/۷۷۰۷۸"
    },
    "3158473": {
        "شناسه  سند": "۲۴۰/۱۰۲۳۱۴",
        "شناسه بازيابي": "۱۳/۱/۱۰۲۳۱۴",
        "عنوان": "مالیات املاک روستاهای بلوک جوشقان کاشان [سند]",
        "سطح استاندارد": "پرونده",
        "منشا": "ایران. وزارت امور اقتصادی و دارایی",
        "تاریخ /دوره ایجاد": "۱۳۰۸.",
        "مشخصات ظاهری": "۱۵ برگ.",
        "دامنه و محتوا": "رسیدگی اداره کل عایدات وزارت مالیه و اداره مالیه کاشان درخصوص وصول مالیات املاک در روستاهای بلوک جوشقان.",
        "توصیفگر": "ایران. وزارت مالیه. اداره مالیه کاشان روستاها\nم‍ال‍ی‍اته‍ا\nملک\nاراضی روستایی کاشان",
        "مركز نگهداري سند": "آرشيو ملي ايران",
        "شناسه سند": "۲۴۰/۱۰۲۳۱۴"
    },
    "3158474": {
        "شناسه  سند": "۲۴۰/۷۷۰۷۹",
        "شناسه بازيابي": "۱۳/۱/۷۷۰۷۹",
        "عنوان": "درخواست تعیین تکلیف قریه خورنین خالصه در قزوین[سند]",
        "سطح استاندارد": "پرونده",
        "منشا": "ایران. وزارت امور اقتصادی و دارایی",
        "تاریخ /دوره ایجاد": "۱۳۳۳.",
        "مشخصات ظاهری": "۱۶ برگ.",
        "دامنه و محتوا": "شکایت رعایای قریه خورنین خالصه قزوین از مطالبات نا عادلانه مالیه از آنها و رسیدگی وزارت مالیه ٬ قرارداد بین دولت به نمایندگی از وثوق الدوله و رعایای قریه مزبور.",
        "توصیفگر": "ایران. وزارت مالیه ش‍ک‍ای‍ت\nق‍رارداد ه‍ا\nاراض‍ی ع‍م‍وم‍ی\nروس‍ت‍ا [۱]\nک‍ش‍اورزان قزوین",
        "مركز نگهداري سند": "آرشيو ملي ايران",
        "شناسه سند": "۲۴۰/۷۷۰۷۹"
    },
    "3158475": {
        "شناسه  سند": "۲۴۰/۷۷۰۸۰",
        "شناسه بازيابي": "۱۳/۱/۷۷۰۸۰",
        "عنوان": "سرقت تیر و سیم ارتباط تلفنی[سند]",
        "سطح استاندارد": "پرونده",
        "منشا": "ایران. وزارت امور اقتصادی و دارایی",
        "تاریخ /دوره ایجاد": "۱۳۲۳.",
        "مشخصات ظاهری": "۳ برگ.",
        "دامنه و محتوا": "سرقت تیر و سیم ارتباط تلفنی در کشور و گزارش آنها.",
        "توصیفگر": "ایران. وزارت دارایی دزدی\nسیم\nخسارت\nش‍رک‍ته‍ای س‍ه‍ام‍ی",
        "مركز نگهداري سند": "آرشيو ملي ايران",
        "شناسه سند": "۲۴۰/۷۷۰۸۰"
    },
    "3158476": {
        "شماره کتابشناسی ملی": "۳۱۵۸۴۷۶",
        "عنوان و  نام پديدآور": "[بزرگداشت شهادت اولین مجاهد خلق احمد رضائی] [اعلامیه]/انجمن دانشجویان مسلمان مدرسه عالی پرستاری بانک ملی",
        "وضعیت نشر": "[بی جا: بی نا،  ۱۳۵۸].",
        "مشخصات ظاهری": "[۱] ورق.",
        "وضعیت فهرست نویسی": "اطلاعات ثبت"
    },
    "3158477": {
        "شناسه  سند": "۲۴۰/۱۰۲۳۱۳",
        "شناسه بازيابي": "۱۳/۱/۱۰۲۳۱۳",
        "عنوان": "جریان کشف قاچاق تریاک توسط کبیری [سند]",
        "سطح استاندارد": "پرونده",
        "منشا": "ایران. وزارت امور اقتصادی و دارایی",
        "تاریخ /دوره ایجاد": "۱۳۱۸.",
        "مشخصات ظاهری": "۹ برگ.",
        "دامنه و محتوا": "بررسی جریان و کیفیت کشف قاچاق ترياک توسط کبیری و زندانی شدن وی و شکایت همسرش از زندانی شدن وی.",
        "توصیفگر": "ق‍اچ‍اق\nتریاک\nش‍ک‍ای‍ت\nزن‍دان‍یک‍ردن مازندران",
        "مركز نگهداري سند": "آرشيو ملي ايران",
        "شناسه سند": "۲۴۰/۱۰۲۳۱۳"
    },
    "3158478": {
        "شناسه  سند": "۲۴۰/۷۷۰۸۱",
        "شناسه بازيابي": "۱۳/۱/۷۷۰۸۱",
        "عنوان": "صورت عیدی خدمتگزاران جزء انتفاعی و اداری اقتصادی زابل[سند]",
        "سطح استاندارد": "پرونده",
        "منشا": "ایران. وزارت امور اقتصادی و دارایی",
        "تاریخ /دوره ایجاد": "۱۳۲۰.",
        "مشخصات ظاهری": "۵ برگ.",
        "دامنه و محتوا": "صورت عیدی خدمتگزاران جزء انتفاعی و اداری اقتصادی زابل و دستور پرداخت آن.",
        "توصیفگر": "ایران. وزارت دارایی پ‍اداش\nاجازهنامهها و پروانهها\nآداب و رسوم \nک‍ارک‍ن‍ان دول‍ت زابل",
        "مركز نگهداري سند": "آرشيو ملي ايران",
        "شناسه سند": "۲۴۰/۷۷۰۸۱"
    },
    "3158479": {
        "شناسه  سند": "۲۴۰/۷۷۰۸۲",
        "شناسه بازيابي": "۱۳/۱/۷۷۰۸۲",
        "عنوان": "شکایت اهالی طارم از روند اخذ مالیات خود توسط مالیه قزوین[سند]",
        "سطح استاندارد": "پرونده",
        "منشا": "ایران. وزارت امور اقتصادی و دارایی",
        "تاریخ /دوره ایجاد": "۱۳۳۳-۱۳۳۴.",
        "مشخصات ظاهری": "۲۷ برگ.",
        "دامنه و محتوا": "بررسی شکایت اهالی طارم از روند غیر عادلانه اخذ مالیات از خود پس از پیوستن به مالیه قزوین.",
        "توصیفگر": "ایران. وزارت دارایی م‍ال‍ی‍اته‍ا\nش‍ک‍ای‍ت قزوین\nطارم",
        "مركز نگهداري سند": "آرشيو ملي ايران",
        "شناسه سند": "۲۴۰/۷۷۰۸۲"
    },
    "3158480": {
        "شناسه  سند": "۲۴۰/۱۰۲۳۱۲",
        "شناسه بازيابي": "۱۳/۱/۱۰۲۳۱۲",
        "عنوان": "کشف تریاک از منزل خویشاوندان رئیس خرید تریاک ملایر [سند]",
        "سطح استاندارد": "پرونده",
        "منشا": "ایران. وزارت امور اقتصادی و دارایی",
        "تاریخ /دوره ایجاد": "۱۳۱۸.",
        "مشخصات ظاهری": "۹ برگ.",
        "دامنه و محتوا": " تکذیب گزارش درخصوص کشف تریاک قاچاق در منزل خویشاوندان پرورش رئیس بخش خرید تریاک ملایر.",
        "توصیفگر": "تریاک\nق‍اچ‍اق\nگ‍زارش ه‍ا ملایر",
        "مركز نگهداري سند": "آرشيو ملي ايران",
        "شناسه سند": "۲۴۰/۱۰۲۳۱۲",
        "دسترسی و محل الکترونیکی": " Ø¢Ø¯Ø±Ø³ Ø§ÙÚ©ØªØ±ÙÙÛÚ©Û ÙÙØ¨Ø¹ "
    },
    "3158481": {
        "شناسه  سند": "۲۴۰/۷۷۰۸۳",
        "شناسه بازيابي": "۱۳/۱/۷۷۰۸۳",
        "عنوان": "پرداخت بهای تادیه صندوق های خالی چوبی کارخانجات دخانیات[سند]",
        "سطح استاندارد": "پرونده",
        "منشا": "ایران. وزارت امور اقتصادی و دارایی",
        "تاریخ /دوره ایجاد": "۱۳۲۰.",
        "مشخصات ظاهری": "۱۳۴ برگ.",
        "دامنه و محتوا": "پرداخت بهای تادیه صندوق های خالی چوبی کارخانجات دخانیات.",
        "توصیفگر": "ایران. وزارت دارایی\nبانک ملی ایران ق‍ی‍م‍ت ه‍ا\nآم‍ار\nکالاها\nدخانیات\nک‍ارخ‍ان‍هه‍ا",
        "مركز نگهداري سند": "آرشيو ملي ايران",
        "شناسه سند": "۲۴۰/۷۷۰۸۳"
    },
    "3158482": {
        "شناسه  سند": "۲۴۰/۱۰۲۳۱۱",
        "شناسه بازيابي": "۱۳/۱/۱۰۲۳۱۱",
        "عنوان": "شرایط فروش توتون برای افراد بیبضاعت اصفهان [سند]",
        "سطح استاندارد": "پرونده",
        "منشا": "ایران. وزارت امور اقتصادی و دارایی",
        "تاریخ /دوره ایجاد": "۱۳۱۸.",
        "مشخصات ظاهری": "۸ برگ.",
        "دامنه و محتوا": "شرایط فروش توتون برای افراد بیبضاعت و چگونگی دسترسی افراد متقاضی در اصفهان.",
        "توصیفگر": "ف‍ق‍را\nف‍روش\nم‍ح‍روم‍ان ج‍ام‍ع‍ه\nتوتون اصفهان",
        "مركز نگهداري سند": "آرشيو ملي ايران",
        "شناسه سند": "۲۴۰/۱۰۲۳۱۱"
    },
    "3158483": {
        "شناسه  سند": "۲۴۰/۱۰۲۳۱۰",
        "شناسه بازيابي": "۱۳/۱/۱۰۲۳۱۰",
        "عنوان": "دستور جلوگیری از عدم کوتاهی در حین انجام وظایف اداره مالیه سمنان و دامغان [سند]",
        "سطح استاندارد": "پرونده",
        "منشا": "ایران. وزارت امور اقتصادی و دارایی",
        "تاریخ /دوره ایجاد": "۱۳۱۵.",
        "مشخصات ظاهری": "۱۵ برگ.",
        "دامنه و محتوا": "تاکید و دستور وزیر مالیه به اداره مالیه سمنان و دامغان مبنی بر عدم کوتاهی در حین انجام وظیفه اداری و قانونی خویش.",
        "توصیفگر": "ایران. وزارت مالیه. اداره مالیه سمنان م‍ق‍ررات اداری\nوظای‍ف اداری\nم‍دی‍ری‍ت اداری سمنان\nدامغان",
        "مركز نگهداري سند": "آرشيو ملي ايران",
        "شناسه سند": "۲۴۰/۱۰۲۳۱۰"
    },
    "3158484": {
        "شناسه  سند": "۲۴۰/۱۰۲۳۰۹",
        "شناسه بازيابي": "۱۳/۱/۱۰۲۳۰۹",
        "عنوان": "صورت بدهی اعضاء هیات نظارت بر شرکت سهامی مرکزی [سند]",
        "سطح استاندارد": "پرونده",
        "منشا": "ایران. وزارت امور اقتصادی و دارایی",
        "تاریخ /دوره ایجاد": "۱۳۱۶ـ۱۳۱۸.",
        "مشخصات ظاهری": "۴۱ برگ.",
        "دامنه و محتوا": "صورت بدهی اعضاء هیات نظارت بر شرکت سهامی مرکزی، بدهی تلفنچی سابق اداره نظارت شرکتها به شرکت سهامی مرکزی.",
        "توصیفگر": "ایران. وزارت بازرگانی\nشرکت سهامی مرکزی دی‍ون\nک‍ارک‍ن‍ان دول‍ت\nح‍ق‍وق و دس‍ت‍م‍زده‍ا\nش‍رک‍ته‍ای س‍ه‍ام‍ی",
        "مركز نگهداري سند": "آرشيو ملي ايران",
        "شناسه سند": "۲۴۰/۱۰۲۳۰۹"
    },
    "3158485": {
        "شناسه  سند": "۲۴۰/۱۰۲۳۰۸",
        "شناسه بازيابي": "۱۳/۱/۱۰۲۳۰۸",
        "عنوان": "مقررات وصول درآمدهای کشوری [سند]",
        "سطح استاندارد": "پرونده",
        "منشا": "ایران. وزارت امور اقتصادی و دارایی",
        "تاریخ /دوره ایجاد": "۱۳۱۵.",
        "مشخصات ظاهری": "۱۶ برگ.",
        "دامنه و محتوا": "رونوشت بخشنامه وزارت مالیه درمورد مقررات مربوط به وصول درآمدهای کشوری و عدم تاخیر در تحویل آن.",
        "توصیفگر": "ایران. وزارت مالیه بخشنامهها\nدرآم‍ده‍ا[۱]\nک‍ارک‍ن‍ان دول‍ت\nوظای‍ف اداری\nش‍رح وظای‍ف\nم‍ق‍ررات اداری",
        "مركز نگهداري سند": "آرشيو ملي ايران",
        "شناسه سند": "۲۴۰/۱۰۲۳۰۸"
    },
    "3158486": {
        "شماره کتابشناسی ملی": "۳۱۵۸۴۸۶",
        "عنوان و  نام پديدآور": "[سازماندهی و تشکیلات دانشجویان مسلمان پلی تکنیک] [اعلامیه]",
        "وضعیت نشر": "[بی جا: بی نا،  ××۱۳].",
        "مشخصات ظاهری": "[۱] ورق.",
        "وضعیت فهرست نویسی": "اطلاعات ثبت"
    },
    "3158487": {},
    "3158488": {
        "شناسه  سند": "۲۴۰/۱۰۲۳۰۷",
        "شناسه بازيابي": "۱۳/۱/۱۰۲۳۰۷",
        "عنوان": "وضعیت مالیات بر درآمد جهرم و اجارهنامه مالیاتهای غیرمستقیم در بم [سند]",
        "سطح استاندارد": "پرونده",
        "منشا": "ایران. وزارت امور اقتصادی و دارایی",
        "تاریخ /دوره ایجاد": "۱۳۰۳ـ۱۳۱۸.",
        "مشخصات ظاهری": "۵۶ برگ.",
        "يادداشت": "تعدادی از برگهای پرونده به زبان انگلیسی است.",
        "دامنه و محتوا": "اجارهنامه عایدات ذبایح و مالیاتهای غیرمستقیم در بم، وضعیت مالیات بر درآمد جهرم.",
        "توصیفگر": "م‍ال‍ی‍اته‍ای م‍س‍ت‍ق‍ی‍م\nدرآم‍ده‍ا[۱]\nم‍ال‍ی‍اته‍ای غ‍ی‍ر م‍س‍ت‍ق‍ی‍م\nم‍ال‍ی‍ات ب‍ر درآم‍د\nص‍ی‍د و ذب‍اح‍ه\nاجارهنامه جهرم\nبم",
        "مركز نگهداري سند": "آرشيو ملي ايران",
        "شناسه سند": "۲۴۰/۱۰۲۳۰۷"
    },
    "3158489": {
        "شماره کتابشناسی ملی": "۳۱۵۸۴۸۹",
        "عنوان و  نام پديدآور": "[انجمن اسلامی دانشجویان دانشگاه تهران خواهان توجه بیشتری به مسلئل آموزشی و پرورشی هستند] [اعلامیه]/انجمن اسلامی دانشجویان دانشگاه تهران",
        "وضعیت نشر": "[بی جا: بی نا،  ××۱۳].",
        "مشخصات ظاهری": "[۱] ورق.",
        "وضعیت فهرست نویسی": "اطلاعات ثبت"
    },
    "3158490": {},
    "3158491": {
        "شماره کتابشناسی ملی": "۳۱۵۸۴۹۱",
        "عنوان و  نام پديدآور": "[اعلامیه گروهی از دانش آموزان دبیرستان ابوسعید] [اعلامیه]",
        "وضعیت نشر": "[بی جا: بی نا،  ××۱۳].",
        "مشخصات ظاهری": "[۱] ورق.",
        "وضعیت فهرست نویسی": "اطلاعات ثبت"
    },
    "3158492": {
        "شناسه  سند": "۲۴۰/۱۰۲۳۰۶",
        "شناسه بازيابي": "۱۳/۱/۱۰۲۳۰۶",
        "عنوان": "رونوشت بخشنامه وزارت دارایی درمورد رعایت تهیه نامهها، نامههای اقتصادی به نیشابور [سند]",
        "سطح استاندارد": "پرونده",
        "منشا": "ایران. وزارت امور اقتصادی و دارایی",
        "تاریخ /دوره ایجاد": "۱۳۱۹ـ۱۳۲۰.",
        "مشخصات ظاهری": "۲۱ برگ.",
        "دامنه و محتوا": "رونوشت بخشنامه وزارت دارایی درمورد اتخاذ روش معین در شکل نامههای اداری.",
        "توصیفگر": "ایران. وزارت دارایی م‍ق‍ررات اداری\nبخشنامهها\nنامهنگاری اداری نیشابور",
        "مركز نگهداري سند": "آرشيو ملي ايران",
        "شناسه سند": "۲۴۰/۱۰۲۳۰۶"
    },
    "3158493": {
        "شماره کتابشناسی ملی": "۳۱۵۸۴۹۳",
        "عنوان و  نام پديدآور": "[بیانیه شماره ۲ [کانون فرهنگی دانش آموزان شهر ری] [اعلامیه]/کانون فرهنگی دانش آموزان شهر ری",
        "وضعیت نشر": "[بی جا: بی نا،  ××۱۳].",
        "مشخصات ظاهری": "[۱] ورق.",
        "وضعیت فهرست نویسی": "اطلاعات ثبت"
    },
    "3158494": {
        "شماره کتابشناسی ملی": "۳۱۵۸۴۹۴",
        "عنوان و  نام پديدآور": "[اعلامیه انجمن دانش آموزان مسلمان دبیرستان محبوبه دانش (هشترودی)] [اعلامیه]/انجمن دانش آموزان مسلمان دبیرستان محبوبه دانش (هشترودی)",
        "وضعیت نشر": "[بی جا: بی نا،  ××۱۳].",
        "مشخصات ظاهری": "[۱] ورق.",
        "وضعیت فهرست نویسی": "اطلاعات ثبت"
    },
    "3158495": {
        "شناسه  سند": "۲۴۰/۱۰۲۳۰۵",
        "شناسه بازيابي": "۱۳/۱/۱۰۲۳۰۵",
        "عنوان": "رونوشت بخشنامههای وزارت دارایی درخصوص ارسال تلگراف و تعیین قیمت آنها [سند]",
        "سطح استاندارد": "پرونده",
        "منشا": "ایران. وزارت امور اقتصادی و دارایی",
        "تاریخ /دوره ایجاد": "۱۳۱۹ـ۱۳۲۲.",
        "مشخصات ظاهری": "۱۲ برگ.",
        "دامنه و محتوا": "رونوشت بخشنامههای وزارت دارایی به اداره دارایی نیشابور درخصوص رعایت شرایط تلگراف مبنی بر اهمیت ماموریت، اختصار و شیوه تنظیم آنها و صرفهجوئی در مصرف کاغذ.",
        "توصیفگر": "ایران. وزارت دارایی کاغذ\nبخشنامهها\nس‍ازم‍انه‍ای دول‍ت‍ی\nت‍ل‍گ‍راف\nص‍رف‍هج‍وی‍ی\nم‍ق‍ررات اداری\nت‍ص‍وی‍بن‍ام‍هها نیشابور\nمشهد",
        "مركز نگهداري سند": "آرشيو ملي ايران",
        "شناسه سند": "۲۴۰/۱۰۲۳۰۵"
    },
    "3158496": {
        "شماره کتابشناسی ملی": "۳۱۵۸۴۹۶",
        "عنوان و  نام پديدآور": "[یاری خواستن  رئیس دبیرستان البرز از دانش آموزان و اولیاء آنها] [اعلامیه]/پور زاهد",
        "وضعیت نشر": "[بی جا: بی نا، ۱۳۵۸].",
        "مشخصات ظاهری": "۲ص.",
        "وضعیت فهرست نویسی": "اطلاعات ثبت"
    },
    "3158497": {
        "شناسه  سند": "۲۴۰/۱۰۲۳۰۴",
        "شناسه بازيابي": "۱۳/۱/۱۰۲۳۰۴",
        "عنوان": "ارسال راهنمای بایگانی وزارت دارایی [سند]",
        "سطح استاندارد": "پرونده",
        "منشا": "ایران. وزارت امور اقتصادی و دارایی",
        "تاریخ /دوره ایجاد": "۱۳۱۹ـ۱۳۲۰.",
        "مشخصات ظاهری": "۴ برگ.",
        "دامنه و محتوا": "راهنمای بایگانی وزارت دارایی شامل درآمدها، هزینهها، عملیات مالی، رونوشت بخشنامههای وزارت دارایی درخصوص ارسال راهنمای بایگانی وزارت دارایی به ادارات شهرستانها.",
        "توصیفگر": "ایران. وزارت دارایی شهرها و شهرستانها\nدرآم‍ده‍ا[۱]\nه‍زی‍ن‍ه ه‍ا\nراه‍ن‍م‍اه‍ا\nس‍ف‍ارتخ‍ان‍هه‍ا\nم‍ال‍ی‍اته‍ای غ‍ی‍ر م‍س‍ت‍ق‍ی‍م\nم‍ال‍ی‍اته‍ای م‍س‍ت‍ق‍ی‍م",
        "مركز نگهداري سند": "آرشيو ملي ايران",
        "شناسه سند": "۲۴۰/۱۰۲۳۰۴"
    },
    "3158498": {
        "شماره کتابشناسی ملی": "۳۱۵۸۴۹۸",
        "عنوان و  نام پديدآور": "[اعلام پشتیبانی از دانشجویان مسلمان پیرو خط امام] [اعلامیه]/انجمن دانش آموزان مسلمان دبیرستان مقداد",
        "وضعیت نشر": "[بی جا: بی نا،  ××۱۳].",
        "مشخصات ظاهری": "[۱] ورق.",
        "وضعیت فهرست نویسی": "اطلاعات ثبت"
    },
    "3158499": {
        "شماره کتابشناسی ملی": "۳۱۵۸۴۹۹",
        "عنوان و  نام پديدآور": "[آشنایی با فن تکثیر] [اعلامیه]",
        "وضعیت نشر": "[بی جا: بی نا،  ××۱۳].",
        "مشخصات ظاهری": "[۲]ص.",
        "وضعیت فهرست نویسی": "اطلاعات ثبت"
    },
    "3158500": {
        "عنوان": "قطع نامه كميسيون مشترك ايران و آمريكا جهت تجهيزات هواپيمايي و...",
        "سطح استاندارد": "پرونده",
        "منشا": "گ‍ن‍ج‍ی، م‍ح‍م‍د ح‍س‍ن، ۱۲۹۱ - ۱۳۹۱.",
        "تاریخ /دوره ایجاد": "۱۳۳۶.۱۹۵۷م.",
        "مشخصات ظاهری": "نقشه.\nروزنامه.\n۲۱۱ برگ.",
        "يادداشت": "قسمتی از اسناد به زبان انگلیسی می باشد.",
        "دامنه و محتوا": "كپي هادرخصوص قطع نامه كميسيون مشترك ايران و آمريكا جهت تجهيزات هواپيمايي و هواشناسي، شهادتنامه دوره دكتري جغرافياي احمد نصير تفرشي با عنوان كيفيت پيدايش و تاريخچه شهرهاي اطراف تهران زير نظر دكتر گنجي و....",
        "توصیفگر": "گ‍ن‍ج‍ی، م‍ح‍م‍د ح‍س‍ن، ۱۲۹۱ - ۱۳۹۱. دان‍ش‍ج‍وی‍ان\nابزار و تجهیزات\nهواشناسی آمریکا\nافغانستان \nایران",
        "مركز نگهداري سند": "آرشيو ملي ايران",
        "شناسه سند": "۹۹۸/۴۸۶۲",
        "دسترسی و محل الکترونیکی": " Ø¢Ø¯Ø±Ø³ Ø§ÙÚ©ØªØ±ÙÙÛÚ©Û ÙÙØ¨Ø¹ "
    }
}